Workbook

Sheet Notes
C5: Scope The IEA produced this dataset as part of efforts to track advances in carbon capture, utilisation, and storage (CCUS). It covers all CO2 capture, transport, storage, and utilisation projects worldwide that have been commissioned since the 1970s, with an announced capacity of more than 100 000 t per year (or 1000 t per year for direct air capture facilities). It includes projects with a clear emissions reduction scope, and excludes CO2 capture for utilisation pathways which bring low climate benefits (e.g. food and beverages) or which are part of the conventional industrial process (e.g. internal use for urea production), as well as use of naturally occurring CO2 for enhanced oil recovery (EOR). When the capacity is unknown, only projects with a clear commercial scope are included. If an industrial cluster has been announced, only identified CO2 capture projects within this cluster are included (i.e. it does not include the full potential capture capacity of industrial clusters for which capture sources are not specified). Capture projects for CO2 use are included as long as the source of the CO2 (i.e. capture facility) has been clearly identified. Projects are categorised by type (capture, full chain, transport, storage, CCU), sector of point source (fuel transformation, power and heat, industry, direct air capture, etc.), and fate of CO2 (dedicated storage, EOR, utilisation, unknown/unspecified). Detailed definitions for each column are available in the Definitions tab. Project announcements as of February 2024 are included. Data Data collection and processing by the IEA. All public references are available by project. Notes on how to aggregate the data are available in Aggregation notes. For any feedback or questions please contact ccsinfo@iea.org. Citation Please cite this database as: IEA (2024), CCUS Projects Database, https://www.iea.org/data-and-statistics/data-product/ccus-projects-database

Sheet Definitions_and_assumptions
B6: Country | C6: Country of project location.
B8: Project partners | C8: Includes project developers, technology providers (''tech''), and contractors, including for feasibility, front-end engineering and design (FEED), equipment procurement and construction (EPC), etc. when applicable/known.
B10: Project type
B12: Full chain | C12: Projects where CO2 is transported from one capture facility to one injection site, typically involving a single operator.
B13: Capture | C13: Capture-only project (project does not include any transport and storage development but can be developed as part of a CCUS hub).
B14: Transport | C14: CO2 transport-only project, which may include CO2 shipping, pipelines, terminals with liquefaction stations/buffer storage, etc.
B15: Storage | C15: CO2 storage-only project (no mention of connecting infrastructure), including both dedicated storage and CO2 enhanced oil recovery (EOR).
B16: T&S | C16: CO2 transport and storage project which includes both transport and storage development.
B17: CCU | C17: A project that captures CO2 for use (excluding internal use such as urea production) with significant climate benefits and a clearly identified source for the captured CO2.
B19: Dates
B21: Announcement | C21: Year of project announcement.
B22: FID | C22: Actual or planned year of final investment decision (FID).
B23: Operation | C23: Actual or planned year of project commissioning.
B24: Suspension/decommissioning | C24: Actual year of suspension/decommissioning.
B26: Project status
B28: Planned | C28: Project at concept, feasibility or engineering study (FEED) stage. Concept projects include announcements with little to no further information available (e.g. capture technology, site, stakeholders, budget, timeline).
B29: Under construction | C29: A final investment decision (FID) has been announced and construction is ongoing or imminent.
B30: Operational | C30: Project has been commissioned and is running.
B31: Suspended | C31: Project operation is suspended for more than six months.
B32: Decommissioned | C32: Project operation is permanently stopped.
B34: Project Phase | C34: If projects have defined announced phases or plan to develop capacity in a stepwise manner, this column is used. Phasing starts from 1. Announced capacity across phases is additional, not cumulative.
B36: Announced capacity (Mt CO2 per year) | C36: Announced or actual capture, transport and/or storage CO2 capacity, in Mt CO2 per year. When capture capacity is announced as a range, or several values are available, announced capacity is entered as a range.
B38: Estimated capacity by IEA (Mt CO2 per year) | C38: Estimated capture capacity based on other plant details (e.g. fuel production capacity) or potential deployment plans. See conversion factors for further assumptions.
B40: Sector | C40: These sector categories will be published in the online version. For capture, full chain, and CCU projects, the sector corresponds to the source of capture.
B42: Power and heat | C42: Capture, full chain, and CCU projects which capture CO2 from power and heat facilities (includes waste-to-energy plants).
B43: Natural gas processing/LNG | C43: Capture, full chain, and CCU projects which capture CO2 from natural gas processing and liquefied natural gas (LNG) trains.
B44: Biofuels | C44: Capture, full chain, and CCU projects which capture CO2 from bioethanol, biodiesel, and biogas facilities.
... B54: T&S | C54: CO2 transport and storage project.
B56: Fate of carbon
B58: Dedicated storage | C58: CO2 is injected deep underground and stored permanently in a dedicated storage site.
B59: EOR | C59: CO2 is used for enhanced oil recovery.
B60: Use | C60: CO2 is used in a product with significant climate benefits. Internal use (e.g. CO2 capture and use in urea production) is excluded.
B61: Unknown/unspecified | C61: Fate of carbon has not been communicated.
B63: Part of CCUS hub
B65: If a capture, transport or storage project is developed as part of a CCUS hub (capture facilities connected to a network of CO2 storage sites by shared transport infrastructure), the name of the corresponding hub is indicated.
B67: Total capture capacity (Mt CO2 per year) | C67: sum (Estimated capacity) for full chain (''Full chain''), capture (''Capture'') and utilisation ("CCU") projects across phases, excluding suspended and decommissioned projects.
B69: Total storage capacity (Mt CO2 per year) | C69: sum (Estimated capacity) for full chain (''Full chain''), transport and storage (''T&S''), and storage (''Storage'') projects across phases, excluding suspended and decommissioned projects.
B71: Number of capture facilities | C71: count full chain (''Full chain''), capture (''Capture''), and utilisation ("CCU") projects excluding phases 2, 3, and 4, and suspended and decommissioned projects.
B73: Important note on transport: | C73: transport capacity of individual projects is not cumulative and cannot be summed.
B75: Conversion factors | C75: For projects when CO2 captured capacity is not provided but other details are provided e.g. fuel production capacity (hydrogen, ammonia, e-fuel), captured capacity can be estimated by IEA using the following assumptions:
C77: CO₂ emissions of natural gas fuelled hydrogen plants: 0.9105 kg CO₂/nm³ H₂. Source: California Air Resources Board, 2018.
C78: CO₂ emissions of coal fuelled hydrogen plants: 1.9075 kg CO₂/nm³ H₂. Source: Orhan and Alper, 2014; adjusted for hydrogen production only.
C79: Specific H2 requirement for NH3 (t/t): 0.180072; Conversion losses 2%.
C80: H2 density in standard conditions: 0.089 kg/m3.

Sheet Aggregation_notes
B6: Total capture capacity (Mt CO2 per year) | C6: sum (Estimated capacity) for full chain (''Full chain''), capture (''Capture'') and utilisation ("CCU") projects across phases, excluding suspended and decommissioned projects.
B8: Total storage capacity (Mt CO2 per year) | C8: sum (Estimated capacity) for full chain (''Full chain''), transport and storage (''T&S''), and storage (''Storage'') projects across phases, excluding suspended and decommissioned projects.
B10: Number of capture facilities | C10: count full chain (''Full chain''), capture (''Capture''), and utilisation ("CCU") projects excluding phases 2, 3, and 4, and suspended and decommissioned projects.
B12: Important note on transport: | C12: transport capacity of individual projects is not cumulative and cannot be summed.

Sheet CCUS_Projects_Database
A1: Project name | B1: ID | C1: Country | D1: Partners | E1: Project type | F1: Announcement | G1: FID | H1: Operation | I1: Suspension/decommissioning | J1: Project Status | K1: Project phase | L1: Announced capacity (Mt CO2/yr) | M1: Estimated capacity by IEA (Mt CO2/yr) | N1: Sector | O1: Fate of carbon | P1: Part of CCUS hub | Q1: Region | R1: Ref 1 | S1: Ref 2 | T1: Ref 3 | U1: Ref 4 | V1: Ref 5 | W1: Ref 6 | X1: Ref 7 | Y1: Link 1 | Z1: Link 2 | AA1: Link 3 | AB1: Link 4 | AC1: Link 5 | AD1: Link 6 | AE1: Link 7
A2: 3D DMX ArcelorMittal and IFPEN Dunkirk 'REUZE' | B2: 751 | C2: France | D2: ArcelorMittal, Engie, Infinium | E2: CCU | F2: 2022 | G2: 2024 | H2: 2025 | J2: Planned | K2: 1 | L2: 0.3 | M2: 0.3 | N2: Iron and steel | O2: Use | Q2: Europe | R2: https://newsroom.engie.com/actualites/engie-et-infinium-annoncent-un-partenariat-pour-developper-un-hub-industriel-denvergure-europeenne-de-production-de-carburants-de-synthese-a-dunkerque-6d4d-ff316.html | S2: https://corporate.arcelormittal.com/climate-action/decarbonisation-technologies/the-3d-project-dmx-demonstration-in-dunkirk | Y2: =IF(CCUS_Projects_Database!$R3<>"",HYPERLINK(CCUS_Projects_Database!$R3,"Link 1"),"") -> Link 1 | Z2: =IF(CCUS_Projects_Database!$S3<>"",HYPERLINK(CCUS_Projects_Database!$S3,"Link 2"),"") -> Link 2 | AA2: =IF(CCUS_Projects_Database!$T3<>"",HYPERLINK(CCUS_Projects_Database!$T3,"Link 3"),"") | AB2: =IF(CCUS_Projects_Database!$U3<>"",HYPERLINK(CCUS_Projects_Database!$U3,"Link 4"),"") | AC2: =IF(CCUS_Projects_Database!$V3<>"",HYPERLINK(CCUS_Projects_Database!$V3,"Link 5"),"") | AD2: =IF(CCUS_Projects_Database!$W3<>"",HYPERLINK(CCUS_Projects_Database!$W3,"Link 6"),"") | AE2: =IF(CCUS_Projects_Database!$X3<>"",HYPERLINK(CCUS_Projects_Database!$X3,"Link 7"),"")
A3: 3D DMX ArcelorMittal and IFPEN Dunkirk (full-scale) | B3: 1 | C3: France | D3: ArcelorMittal, ifp, Axens, Uetikon, Grassco, brevik, TotalEnergies (T&S) | E3: Capture | F3: 2019 | H3: 2025 | J3: Planned | K3: 2 | L3: 0.7 | M3: 0.7 | N3: Iron and steel | O3: Unknown/unspecified | Q3: Europe | R3: https://automotive.arcelormittal.com/news_and_stories/news/2019DMXproject | S3: https://3d-ccus.com/3d-overview/ | Y3: =IF(CCUS_Projects_Database!$R2<>"",HYPERLINK(CCUS_Projects_Database!$R2,"Link 1"),"") -> Link 1 | Z3: =IF(CCUS_Projects_Database!$S2<>"",HYPERLINK(CCUS_Projects_Database!$S2,"Link 2"),"") -> Link 2 | AA3: =IF(CCUS_Projects_Database!$T2<>"",HYPERLINK(CCUS_Projects_Database!$T2,"Link 3"),"") | AB3: =IF(CCUS_Projects_Database!$U2<>"",HYPERLINK(CCUS_Projects_Database!$U2,"Link 4"),"") | AC3: =IF(CCUS_Projects_Database!$V2<>"",HYPERLINK(CCUS_Projects_Database!$V2,"Link 5"),"") | AD3: =IF(CCUS_Projects_Database!$W2<>"",HYPERLINK(CCUS_Projects_Database!$W2,"Link 6"),"") | AE3: =IF(CCUS_Projects_Database!$X2<>"",HYPERLINK(CCUS_Projects_Database!$X2,"Link 7"),"")
A4: 7 Blue Ammonia Facility | B4: 1055 | C4: Qatar | D4: QAFCO, thyssenkrupp Uhde/Consolidated Contractors Company (EPC) | E4: Full Chain | F4: 2022 | G4: 2022 | H4: 2026 | J4: Under construction | L4: 1.5 | M4: 1.5 | N4: Hydrogen or ammonia | O4: Unknown/unspecified | Q4: Middle East | R4: https://www.qafco.qa/content/qafco-7-announcement | S4: https://www.thyssenkrupp.com/en/newsroom/press-releases/pressdetailpage/thyssenkrupp-uhde-to-build-world-scale-blue-ammonia-plant-in-qatar-138369 | Y4: =IF(CCUS_Projects_Database!$R4<>"",HYPERLINK(CCUS_Projects_Database!$R4,"Link 1"),"") -> Link 1 | Z4: =IF(CCUS_Projects_Database!$S4<>"",HYPERLINK(CCUS_Projects_Database!$S4,"Link 2"),"") -> Link 2 | AA4: =IF(CCUS_Projects_Database!$T4<>"",HYPERLINK(CCUS_Projects_Database!$T4,"Link 3"),"") | AB4: =IF(CCUS_Projects_Database!$U4<>"",HYPERLINK(CCUS_Projects_Database!$U4,"Link 4"),"") | AC4: =IF(CCUS_Projects_Database!$V4<>"",HYPERLINK(CCUS_Projects_Database!$V4,"Link 5"),"") | AD4: =IF(CCUS_Projects_Database!$W4<>"",HYPERLINK(CCUS_Projects_Database!$W4,"Link 6"),"") | AE4: =IF(CCUS_Projects_Database!$X4<>"",HYPERLINK(CCUS_Projects_Database!$X4,"Link 7"),"")
A5: 8Rivers H2 (8RH2) (WY) | B5: 3 | C5: United States | D5: 8Rivers, Wyoming Energy Authority | E5: Capture | F5: 2022 | J5: Planned | N5: Hydrogen or ammonia | O5: Dedicated storage | Q5: North America | R5: https://8rivers.com/portfolio/8-rivers-hydrogen/# | Y5: =IF(CCUS_Projects_Database!$R5<>"",HYPERLINK(CCUS_Projects_Database!$R5,"Link 1"),"") -> Link 1 | Z5: =IF(CCUS_Projects_Database!$S5<>"",HYPERLINK(CCUS_Projects_Database!$S5,"Link 2"),"") | AA5: =IF(CCUS_Projects_Database!$T5<>"",HYPERLINK(CCUS_Projects_Database!$T5,"Link 3"),"") | AB5: =IF(CCUS_Projects_Database!$U5<>"",HYPERLINK(CCUS_Projects_Database!$U5,"Link 4"),"") | AC5: =IF(CCUS_Projects_Database!$V5<>"",HYPERLINK(CCUS_Projects_Database!$V5,"Link 5"),"") | AD5: =IF(CCUS_Projects_Database!$W5<>"",HYPERLINK(CCUS_Projects_Database!$W5,"Link 6"),"") | AE5: =IF(CCUS_Projects_Database!$X5<>"",HYPERLINK(CCUS_Projects_Database!$X5,"Link 7"),"")
A6: Abadi CCS/CCUS | B6: 227 | C6: Indonesia | D6: Inpex Masela 65%, Shell (trying to find a buyer for its shares), ITB (feasibility) | E6: Full chain | F6: 2018 | H6: 2027 | J6: Planned | L6: 2.41 | M6: 2.41 | N6: Natural gas processing/LNG | O6: Unknown/unspecified | Q6: Other Asia Pacific | R6: https://www.upstreamonline.com/lng/inpex-further-delays-flagship-abadi-lng-project/2-1-1173044 | S6: https://www.ogj.com/pipelines-transportation/lng/article/14292056/inpex-submits-ccs-plan-for-abadi-lng-project | T6: https://www.spglobal.com/commodityinsights/en/market-insights/latest-news/lng/092823-interview-indonesia-to-finalize-presidential-ccsccus-regulation-by-year-end | Y6: =IF(CCUS_Projects_Database!$R6<>"",HYPERLINK(CCUS_Projects_Database!$R6,"Link 1"),"") -> Link 1 | Z6: =IF(CCUS_Projects_Database!$S6<>"",HYPERLINK(CCUS_Projects_Database!$S6,"Link 2"),"") -> Link 2 | AA6: =IF(CCUS_Projects_Database!$T6<>"",HYPERLINK(CCUS_Projects_Database!$T6,"Link 3"),"") -> Link 3 | AB6: =IF(CCUS_Projects_Database!$U6<>"",HYPERLINK(CCUS_Projects_Database!$U6,"Link 4"),"") | AC6: =IF(CCUS_Projects_Database!$V6<>"",HYPERLINK(CCUS_Projects_Database!$V6,"Link 5"),"") | AD6: =IF(CCUS_Projects_Database!$W6<>"",HYPERLINK(CCUS_Projects_Database!$W6,"Link 6"),"") | AE6: =IF(CCUS_Projects_Database!$X6<>"",HYPERLINK(CCUS_Projects_Database!$X6,"Link 7"),"")
A7: Ackerman Combined Cycle Plant (MS) | B7: 975 | C7: United States | D7: Trifecta Renewable Solutions, Tennessee Valley Authority | E7: Capture | F7: 2023 | J7: Planned | L7: 1.8 | M7: 1.8 | N7: Power and heat | O7: Dedicated storage | P7: Red Hills CO2 storage hub (MS) | Q7: North America | R7: https://www.energy.gov/fecm/project-selections-foa-2711-carbon-storage-validation-and-testing-round-2 | Y7: =IF(CCUS_Projects_Database!$R7<>"",HYPERLINK(CCUS_Projects_Database!$R7,"Link 1"),"") -> Link 1 | Z7: =IF(CCUS_Projects_Database!$S7<>"",HYPERLINK(CCUS_Projects_Database!$S7,"Link 2"),"") | AA7: =IF(CCUS_Projects_Database!$T7<>"",HYPERLINK(CCUS_Projects_Database!$T7,"Link 3"),"") | AB7: =IF(CCUS_Projects_Database!$U7<>"",HYPERLINK(CCUS_Projects_Database!$U7,"Link 4"),"") | AC7: =IF(CCUS_Projects_Database!$V7<>"",HYPERLINK(CCUS_Projects_Database!$V7,"Link 5"),"") | AD7: =IF(CCUS_Projects_Database!$W7<>"",HYPERLINK(CCUS_Projects_Database!$W7,"Link 6"),"") | AE7: =IF(CCUS_Projects_Database!$X7<>"",HYPERLINK(CCUS_Projects_Database!$X7,"Link 7"),"")
A8: Acorn CCS phase 1-Capture at St Fergus | B8: 7 | C8: United Kingdom | D8: Storegga(30%), Shell (30%), Harbour (30%), North Sea Midstream partners (10%) | E8: Capture | F8: 2016 | G8: 2024 | H8: 2028 | J8: Planned | L8: 0.3 | M8: 0.3 | N8: Natural gas processing/LNG | O8: Dedicated storage | P8: Acorn CCS | Q8: Europe | R8: https://www.upstreamonline.com/energy-transition/five-proposed-uk-carbon-capture-projects-meet-governments-eligibility-test/2-1-1047222 | S8: https://www.offshore-energy.biz/carbon-clean-to-carry-out-feed-on-acorn-carbon-capture-plant/ | T8: https://www.backthescottishcluster.co.uk/the-scottish-cluster-supply-chain | U8: https://www.storegga.earth/news/2021/news/acorn-project-partners-storegga-shell-u-k-and-harbour-energy-sign-mou-with-the-owners-of-the-segal-and-fuka-gas-terminals-at-st-fergus/ | V8: https://www.scottishconstructionnow.com/articles/acorn-project-partners-select-carbon-clean-to-deliver-st-fergus-carbon-capture-plant-feed-study | W8: https://www.energyvoice.com/oilandgas/north-sea/370332/st-fergus-terminal-owner-joins-acorn-ccs-project-as-partner | Y8: =IF(CCUS_Projects_Database!$R8<>"",HYPERLINK(CCUS_Projects_Database!$R8,"Link 1"),"") -> Link 1 | Z8: =IF(CCUS_Projects_Database!$S8<>"",HYPERLINK(CCUS_Projects_Database!$S8,"Link 2"),"") -> Link 2 | AA8: =IF(CCUS_Projects_Database!$T8<>"",HYPERLINK(CCUS_Projects_Database!$T8,"Link 3"),"") -> Link 3 | AB8: =IF(CCUS_Projects_Database!$U8<>"",HYPERLINK(CCUS_Projects_Database!$U8,"Link 4"),"") -> Link 4 | AC8: =IF(CCUS_Projects_Database!$V8<>"",HYPERLINK(CCUS_Projects_Database!$V8,"Link 5"),"") -> Link 5 | AD8: =IF(CCUS_Projects_Database!$W8<>"",HYPERLINK(CCUS_Projects_Database!$W8,"Link 6"),"") -> Link 6 | AE8: =IF(CCUS_Projects_Database!$X8<>"",HYPERLINK(CCUS_Projects_Database!$X8,"Link 7"),"")
A9: Acorn CCS phase 1-T&S | B9: 8 | C9: United Kingdom | D9: Storegga(30%), Shell (30%), Harbour (30%), North Sea Midstream partners (10%) | E9: T&S | F9: 2016 | G9: 2024 | H9: 2028 | J9: Planned | K9: 1 | L9: 0.55 | M9: 0.8 | N9: T&S | O9: Dedicated storage | P9: Acorn CCS | Q9: Europe | R9: https://www.upstreamonline.com/energy-transition/five-proposed-uk-carbon-capture-projects-meet-governments-eligibility-test/2-1-1047222 | S9: https://www.offshore-energy.biz/carbon-clean-to-carry-out-feed-on-acorn-carbon-capture-plant/ | T9: https://www.backthescottishcluster.co.uk/the-scottish-cluster-supply-chain | U9: https://www.storegga.earth/news/2021/news/acorn-project-partners-storegga-shell-u-k-and-harbour-energy-sign-mou-with-the-owners-of-the-segal-and-fuka-gas-terminals-at-st-fergus/ | V9: https://www.scottishconstructionnow.com/articles/acorn-project-partners-select-carbon-clean-to-deliver-st-fergus-carbon-capture-plant-feed-study | W9: https://www.energyvoice.com/oilandgas/north-sea/370332/st-fergus-terminal-owner-joins-acorn-ccs-project-as-partner | Y9: =IF(CCUS_Projects_Database!$R9<>"",HYPERLINK(CCUS_Projects_Database!$R9,"Link 1"),"") -> Link 1 | Z9: =IF(CCUS_Projects_Database!$S9<>"",HYPERLINK(CCUS_Projects_Database!$S9,"Link 2"),"") -> Link 2 | AA9: =IF(CCUS_Projects_Database!$T9<>"",HYPERLINK(CCUS_Projects_Database!$T9,"Link 3"),"") -> Link 3 | AB9: =IF(CCUS_Projects_Database!$U9<>"",HYPERLINK(CCUS_Projects_Database!$U9,"Link 4"),"") -> Link 4 | AC9: =IF(CCUS_Projects_Database!$V9<>"",HYPERLINK(CCUS_Projects_Database!$V9,"Link 5"),"") -> Link 5 | AD9: =IF(CCUS_Projects_Database!$W9<>"",HYPERLINK(CCUS_Projects_Database!$W9,"Link 6"),"") -> Link 6 | AE9: =IF(CCUS_Projects_Database!$X9<>"",HYPERLINK(CCUS_Projects_Database!$X9,"Link 7"),"")
A10: Acorn CCS phase 2 | B10: 9 | C10: United Kingdom | D10: Storegga(30%), Shell (30%), Harbour (30%), North Sea Midstream partners (10%) | E10: T&S | F10: 2017 | J10: Planned | K10: 2 | L10: 5 | M10: 5 | N10: T&S | O10: Dedicated storage | P10: Acorn CCS | Q10: Europe | R10: https://www.upstreamonline.com/energy-transition/five-proposed-uk-carbon-capture-projects-meet-governments-eligibility-test/2-1-1047222 | S10: https://www.offshore-energy.biz/carbon-clean-to-carry-out-feed-on-acorn-carbon-capture-plant/ | T10: https://www.backthescottishcluster.co.uk/the-scottish-cluster-supply-chain | U10: https://www.storegga.earth/news/2021/news/acorn-project-partners-storegga-shell-u-k-and-harbour-energy-sign-mou-with-the-owners-of-the-segal-and-fuka-gas-terminals-at-st-fergus/ | V10: https://www.scottishconstructionnow.com/articles/acorn-project-partners-select-carbon-clean-to-deliver-st-fergus-carbon-capture-plant-feed-study | W10: https://www.energyvoice.com/oilandgas/north-sea/370332/st-fergus-terminal-owner-joins-acorn-ccs-project-as-partner | X10: https://www.theacornproject.uk/news-and-events/nsta-grants-carbon-storage-licences-to-acorn | Y10: =IF(CCUS_Projects_Database!$R10<>"",HYPERLINK(CCUS_Projects_Database!$R10,"Link 1"),"") -> Link 1 | Z10: =IF(CCUS_Projects_Database!$S10<>"",HYPERLINK(CCUS_Projects_Database!$S10,"Link 2"),"") -> Link 2 | AA10: =IF(CCUS_Projects_Database!$T10<>"",HYPERLINK(CCUS_Projects_Database!$T10,"Link 3"),"") -> Link 3 | AB10: =IF(CCUS_Projects_Database!$U10<>"",HYPERLINK(CCUS_Projects_Database!$U10,"Link 4"),"") -> Link 4 | AC10: =IF(CCUS_Projects_Database!$V10<>"",HYPERLINK(CCUS_Projects_Database!$V10,"Link 5"),"") -> Link 5 | AD10: =IF(CCUS_Projects_Database!$W10<>"",HYPERLINK(CCUS_Projects_Database!$W10,"Link 6"),"") -> Link 6 | AE10: =IF(CCUS_Projects_Database!$X10<>"",HYPERLINK(CCUS_Projects_Database!$X10,"Link 7"),"") -> Link 7
A11: Acorn H2 | B11: 10 | C11: United Kingdom | D11: Storegga, Chrysaor, Shell | E11: Capture | F11: 2018 | H11: 2028 | J11: Planned | L11: 0.4 | M11: 0.4 | N11: Hydrogen or ammonia | O11: Dedicated storage | P11: Acorn CCS | Q11: Europe | R11: https://assets.publishing.service.gov.uk/government/uploads/system/uploads/attachment_data/file/866380/Phase_1_-_Pale_Blue_Dot_Energy_-_Acorn_Hydrogen.pdf | Y11: =IF(CCUS_Projects_Database!$R11<>"",HYPERLINK(CCUS_Projects_Database!$R11,"Link 1"),"") -> Link 1 | Z11: =IF(CCUS_Projects_Database!$S11<>"",HYPERLINK(CCUS_Projects_Database!$S11,"Link 2"),"") | AA11: =IF(CCUS_Projects_Database!$T11<>"",HYPERLINK(CCUS_Projects_Database!$T11,"Link 3"),"") | AB11: =IF(CCUS_Projects_Database!$U11<>"",HYPERLINK(CCUS_Projects_Database!$U11,"Link 4"),"") | AC11: =IF(CCUS_Projects_Database!$V11<>"",HYPERLINK(CCUS_Projects_Database!$V11,"Link 5"),"") | AD11: =IF(CCUS_Projects_Database!$W11<>"",HYPERLINK(CCUS_Projects_Database!$W11,"Link 6"),"") | AE11: =IF(CCUS_Projects_Database!$X11<>"",HYPERLINK(CCUS_Projects_Database!$X11,"Link 7"),"")
A12: Acorn Isle of Grain to Peterhead shipping | B12: 1018 | C12: United Kingdom | D12: Acorn, Uniper | E12: Transport | F12: 2023 | J12: Planned | L12: 2 | M12: 2 | N12: Transport | O12: Dedicated storage | P12: Acorn CCS | Q12: Europe | R12: https://netl.doe.gov/coal/carbon-storage/atlas/secarb | Y12: =IF(CCUS_Projects_Database!$R12<>"",HYPERLINK(CCUS_Projects_Database!$R12,"Link 1"),"") -> Link 1 | Z12: =IF(CCUS_Projects_Database!$S12<>"",HYPERLINK(CCUS_Projects_Database!$S12,"Link 2"),"") | AA12: =IF(CCUS_Projects_Database!$T12<>"",HYPERLINK(CCUS_Projects_Database!$T12,"Link 3"),"") | AB12: =IF(CCUS_Projects_Database!$U12<>"",HYPERLINK(CCUS_Projects_Database!$U12,"Link 4"),"") | AC12: =IF(CCUS_Projects_Database!$V12<>"",HYPERLINK(CCUS_Projects_Database!$V12,"Link 5"),"") | AD12: =IF(CCUS_Projects_Database!$W12<>"",HYPERLINK(CCUS_Projects_Database!$W12,"Link 6"),"") | AE12: =IF(CCUS_Projects_Database!$X12<>"",HYPERLINK(CCUS_Projects_Database!$X12,"Link 7"),"")
A13: Adams Fork Energy clean ammonia project (WV) | B13: 1033 | C13: United States | D13: Adams Fork Energy, the Flandreau Santee Sioux Tribe | E13: Capture | F13: 2022 | G13: 2024 | J13: Planned | M13: 3.591 | N13: Hydrogen or ammonia | O13: Unknown/unspecified | Q13: North America | R13: https://adamsforkenergy.com/ | S13: https://investors.cnx.com/news-releases/2023/04-03-2023-114519172 | T13: https://www.reuters.com/sustainability/cnx-resources-pulls-out-adams-fork-ammonia-project-2023-12-15/ | Y13: =IF(CCUS_Projects_Database!$R13<>"",HYPERLINK(CCUS_Projects_Database!$R13,"Link 1"),"") -> Link 1 | Z13: =IF(CCUS_Projects_Database!$S13<>"",HYPERLINK(CCUS_Projects_Database!$S13,"Link 2"),"") -> Link 2 | AA13: =IF(CCUS_Projects_Database!$T13<>"",HYPERLINK(CCUS_Projects_Database!$T13,"Link 3"),"") -> Link 3 | AB13: =IF(CCUS_Projects_Database!$U13<>"",HYPERLINK(CCUS_Projects_Database!$U13,"Link 4"),"") | AC13: =IF(CCUS_Projects_Database!$V13<>"",HYPERLINK(CCUS_Projects_Database!$V13,"Link 5"),"") | AD13: =IF(CCUS_Projects_Database!$W13<>"",HYPERLINK(CCUS_Projects_Database!$W13,"Link 6"),"") | AE13: =IF(CCUS_Projects_Database!$X13<>"",HYPERLINK(CCUS_Projects_Database!$X13,"Link 7"),"")
A14: Adbri Project | B14: 11 | C14: Australia | D14: Adbri, CarbonTP, Heavy Industry Low Emissions Technology Co-Operative Research Centre | E14: Capture | F14: 2021 | J14: Planned | N14: Cement | O14: Dedicated storage | P14: South West Hub Project | Q14: Australia and New Zealand | R14: https://calix.global/co2-mitigation-focus-area/awarded-11m-in-government-funding-for-low-emissions-lime-project-with-adbri/ | Y14: =IF(CCUS_Projects_Database!$R14<>"",HYPERLINK(CCUS_Projects_Database!$R14,"Link 1"),"") -> Link 1 | Z14: =IF(CCUS_Projects_Database!$S14<>"",HYPERLINK(CCUS_Projects_Database!$S14,"Link 2"),"") | AA14: =IF(CCUS_Projects_Database!$T14<>"",HYPERLINK(CCUS_Projects_Database!$T14,"Link 3"),"") | AB14: =IF(CCUS_Projects_Database!$U14<>"",HYPERLINK(CCUS_Projects_Database!$U14,"Link 4"),"") | AC14: =IF(CCUS_Projects_Database!$V14<>"",HYPERLINK(CCUS_Projects_Database!$V14,"Link 5"),"") | AD14: =IF(CCUS_Projects_Database!$W14<>"",HYPERLINK(CCUS_Projects_Database!$W14,"Link 6"),"") | AE14: =IF(CCUS_Projects_Database!$X14<>"",HYPERLINK(CCUS_Projects_Database!$X14,"Link 7"),"")
A15: ADM Cedar rapids bioethanol (IA) | B15: 13 | C15: United States | D15: ADM | E15: Capture | F15: 2022 | J15: Planned | N15: Biofuels | O15: Dedicated storage | P15: Mt Simon Hub CCS Pipeline (IA) | Q15: North America | R15: https://www.businesswire.com/news/home/20220110006079/en/ | Y15: =IF(CCUS_Projects_Database!$R15<>"",HYPERLINK(CCUS_Projects_Database!$R15,"Link 1"),"") -> Link 1 | Z15: =IF(CCUS_Projects_Database!$S15<>"",HYPERLINK(CCUS_Projects_Database!$S15,"Link 2"),"") | AA15: =IF(CCUS_Projects_Database!$T15<>"",HYPERLINK(CCUS_Projects_Database!$T15,"Link 3"),"") | AB15: =IF(CCUS_Projects_Database!$U15<>"",HYPERLINK(CCUS_Projects_Database!$U15,"Link 4"),"") | AC15: =IF(CCUS_Projects_Database!$V15<>"",HYPERLINK(CCUS_Projects_Database!$V15,"Link 5"),"") | AD15: =IF(CCUS_Projects_Database!$W15<>"",HYPERLINK(CCUS_Projects_Database!$W15,"Link 6"),"") | AE15: =IF(CCUS_Projects_Database!$X15<>"",HYPERLINK(CCUS_Projects_Database!$X15,"Link 7"),"")
A16: ADM Clinton bioethanol (IA) | B16: 14 | C16: United States | D16: ADM | E16: Capture | F16: 2022 | J16: Planned | N16: Biofuels | O16: Dedicated storage | P16: Mt Simon Hub CCS Pipeline (IA) | Q16: North America | R16: https://www.businesswire.com/news/home/20220110006079/en/ | Y16: =IF(CCUS_Projects_Database!$R16<>"",HYPERLINK(CCUS_Projects_Database!$R16,"Link 1"),"") -> Link 1 | Z16: =IF(CCUS_Projects_Database!$S16<>"",HYPERLINK(CCUS_Projects_Database!$S16,"Link 2"),"") | AA16: =IF(CCUS_Projects_Database!$T16<>"",HYPERLINK(CCUS_Projects_Database!$T16,"Link 3"),"") | AB16: =IF(CCUS_Projects_Database!$U16<>"",HYPERLINK(CCUS_Projects_Database!$U16,"Link 4"),"") | AC16: =IF(CCUS_Projects_Database!$V16<>"",HYPERLINK(CCUS_Projects_Database!$V16,"Link 5"),"") | AD16: =IF(CCUS_Projects_Database!$W16<>"",HYPERLINK(CCUS_Projects_Database!$W16,"Link 6"),"") | AE16: =IF(CCUS_Projects_Database!$X16<>"",HYPERLINK(CCUS_Projects_Database!$X16,"Link 7"),"")
A17: ADM Decatur Campus CO2 Storage Site Expansion (IL) | B17: 816 | C17: United States | D17: ADM | E17: T&S | F17: 2022 | H17: 2028 | J17: Planned | K17: 2 | L17: 2.95 | M17: 2.95 | N17: T&S | O17: Dedicated storage | P17: ADM Decatur Campus CO2 Storage Site Expansion (IL) | Q17: North America | Y17: =IF(CCUS_Projects_Database!$R17<>"",HYPERLINK(CCUS_Projects_Database!$R17,"Link 1"),"") | Z17: =IF(CCUS_Projects_Database!$S17<>"",HYPERLINK(CCUS_Projects_Database!$S17,"Link 2"),"") | AA17: =IF(CCUS_Projects_Database!$T17<>"",HYPERLINK(CCUS_Projects_Database!$T17,"Link 3"),"") | AB17: =IF(CCUS_Projects_Database!$U17<>"",HYPERLINK(CCUS_Projects_Database!$U17,"Link 4"),"") | AC17: =IF(CCUS_Projects_Database!$V17<>"",HYPERLINK(CCUS_Projects_Database!$V17,"Link 5"),"") | AD17: =IF(CCUS_Projects_Database!$W17<>"",HYPERLINK(CCUS_Projects_Database!$W17,"Link 6"),"") | AE17: =IF(CCUS_Projects_Database!$X17<>"",HYPERLINK(CCUS_Projects_Database!$X17,"Link 7"),"")
A18: ADM Maroa/Forsyth CO2 Storage Site Development (IL) | B18: 869 | C18: United States | D18: ADM | E18: Storage | F18: 2023 | H18: 2028 | J18: Planned | L18: 3.3 | M18: 3.3 | N18: Storage | O18: Unknown/unspecified | P18: Maroa (IL) | Q18: North America | R18: https://www.epa.gov/uic/current-class-vi-projects-under-review-epa | Y18: =IF(CCUS_Projects_Database!$R18<>"",HYPERLINK(CCUS_Projects_Database!$R18,"Link 1"),"") -> Link 1 | Z18: =IF(CCUS_Projects_Database!$S18<>"",HYPERLINK(CCUS_Projects_Database!$S18,"Link 2"),"") | AA18: =IF(CCUS_Projects_Database!$T18<>"",HYPERLINK(CCUS_Projects_Database!$T18,"Link 3"),"") | AB18: =IF(CCUS_Projects_Database!$U18<>"",HYPERLINK(CCUS_Projects_Database!$U18,"Link 4"),"") | AC18: =IF(CCUS_Projects_Database!$V18<>"",HYPERLINK(CCUS_Projects_Database!$V18,"Link 5"),"") | AD18: =IF(CCUS_Projects_Database!$W18<>"",HYPERLINK(CCUS_Projects_Database!$W18,"Link 6"),"") | AE18: =IF(CCUS_Projects_Database!$X18<>"",HYPERLINK(CCUS_Projects_Database!$X18,"Link 7"),"")
A19: ADNOC CO2 storage hub (Phase 2 of fertiglobe pilot) | B19: 928 | C19: United Arab Emirates | D19: ADNOC | E19: Storage | F19: 2023 | H19: 2030 | J19: Planned | K19: 2 | L19: 5 | M19: 5 | N19: Storage | O19: Dedicated storage | P19: ADNOC CO2 storage hub | Q19: Middle East | R19: https://www.adnoc.ae/en/news-and-media/press-releases/2023/adnoc-announces-world-first-fully-sequestered-co2-injection-project | Y19: =IF(CCUS_Projects_Database!$R19<>"",HYPERLINK(CCUS_Projects_Database!$R19,"Link 1"),"") -> Link 1 | Z19: =IF(CCUS_Projects_Database!$S19<>"",HYPERLINK(CCUS_Projects_Database!$S19,"Link 2"),"") | AA19: =IF(CCUS_Projects_Database!$T19<>"",HYPERLINK(CCUS_Projects_Database!$T19,"Link 3"),"") | AB19: =IF(CCUS_Projects_Database!$U19<>"",HYPERLINK(CCUS_Projects_Database!$U19,"Link 4"),"") | AC19: =IF(CCUS_Projects_Database!$V19<>"",HYPERLINK(CCUS_Projects_Database!$V19,"Link 5"),"") | AD19: =IF(CCUS_Projects_Database!$W19<>"",HYPERLINK(CCUS_Projects_Database!$W19,"Link 6"),"") | AE19: =IF(CCUS_Projects_Database!$X19<>"",HYPERLINK(CCUS_Projects_Database!$X19,"Link 7"),"")
A20: Advanced CO2 Capture from Hydrogen Production Unit at Phillips 66 Rodeo Refinery (CA) | B20: 695 | C20: United States | D20: Phillips 66 | E20: Capture | F20: 2021 | J20: Planned | L20: 0.19 | M20: 0.19 | N20: Other fuel transformation | O20: Unknown/unspecified | Q20: North America | R20: https://www.netl.doe.gov/node/10875 | Y20: =IF(CCUS_Projects_Database!$R20<>"",HYPERLINK(CCUS_Projects_Database!$R20,"Link 1"),"") -> Link 1 | Z20: =IF(CCUS_Projects_Database!$S20<>"",HYPERLINK(CCUS_Projects_Database!$S20,"Link 2"),"") | AA20: =IF(CCUS_Projects_Database!$T20<>"",HYPERLINK(CCUS_Projects_Database!$T20,"Link 3"),"") | AB20: =IF(CCUS_Projects_Database!$U20<>"",HYPERLINK(CCUS_Projects_Database!$U20,"Link 4"),"") | AC20: =IF(CCUS_Projects_Database!$V20<>"",HYPERLINK(CCUS_Projects_Database!$V20,"Link 5"),"") | AD20: =IF(CCUS_Projects_Database!$W20<>"",HYPERLINK(CCUS_Projects_Database!$W20,"Link 6"),"") | AE20: =IF(CCUS_Projects_Database!$X20<>"",HYPERLINK(CCUS_Projects_Database!$X20,"Link 7"),"")
A21: AEB Amsterdam | B21: 1144 | C21: Netherlands | D21: AEB Amsterdam | E21: CCU | F21: 2021 | H21: 2028 | J21: Planned | L21: 0.44 | M21: 0.44 | N21: Power and heat | O21: Use | Q21: Europe | R21: https://www.kn.lt/en/news/news/kn-akmenes-cementas-and-orlen-lietuva-to-evaluate-the-applicability-of-liquefied-co2-capture-technology/5686 | S21: https://www.aebamsterdam.com/technology/ | Y21: =IF(CCUS_Projects_Database!$R21<>"",HYPERLINK(CCUS_Projects_Database!$R21,"Link 1"),"") -> Link 1 | Z21: =IF(CCUS_Projects_Database!$S21<>"",HYPERLINK(CCUS_Projects_Database!$S21,"Link 2"),"") -> Link 2 | AA21: =IF(CCUS_Projects_Database!$T21<>"",HYPERLINK(CCUS_Projects_Database!$T21,"Link 3"),"") | AB21: =IF(CCUS_Projects_Database!$U21<>"",HYPERLINK(CCUS_Projects_Database!$U21,"Link 4"),"") | AC21: =IF(CCUS_Projects_Database!$V21<>"",HYPERLINK(CCUS_Projects_Database!$V21,"Link 5"),"") | AD21: =IF(CCUS_Projects_Database!$W21<>"",HYPERLINK(CCUS_Projects_Database!$W21,"Link 6"),"") | AE21: =IF(CCUS_Projects_Database!$X21<>"",HYPERLINK(CCUS_Projects_Database!$X21,"Link 7"),"")
A22: Aemetis CCS (CA) | B22: 814 | C22: United States | D22: Aemetis Carbon Capture (Aemetis) | E22: Storage | F22: 2021 | H22: 2024 | J22: Planned | L22: 1.7 | M22: 1.4 | N22: Storage | O22: Dedicated storage | P22: Aemetis CCS | Q22: North America | R22: https://www.aemetis.com/products/carbon-capture/ | S22: https://www.aemetis.com/aemetis-awarded-the-first-co2-sequestration-characterization-well-permit-issued-by-the-state-of-california/ | Y22: =IF(CCUS_Projects_Database!$R22<>"",HYPERLINK(CCUS_Projects_Database!$R22,"Link 1"),"") -> Link 1 | Z22: =IF(CCUS_Projects_Database!$S22<>"",HYPERLINK(CCUS_Projects_Database!$S22,"Link 2"),"") -> Link 2 | AA22: =IF(CCUS_Projects_Database!$T22<>"",HYPERLINK(CCUS_Projects_Database!$T22,"Link 3"),"") | AB22: =IF(CCUS_Projects_Database!$U22<>"",HYPERLINK(CCUS_Projects_Database!$U22,"Link 4"),"") | AC22: =IF(CCUS_Projects_Database!$V22<>"",HYPERLINK(CCUS_Projects_Database!$V22,"Link 5"),"") | AD22: =IF(CCUS_Projects_Database!$W22<>"",HYPERLINK(CCUS_Projects_Database!$W22,"Link 6"),"") | AE22: =IF(CCUS_Projects_Database!$X22<>"",HYPERLINK(CCUS_Projects_Database!$X22,"Link 7"),"")
A23: Aemetis CCS Keyes facility (CA) | B23: 15 | C23: United States | D23: Aemetis | E23: Capture | F23: 2021 | H23: 2024 | J23: Planned | L23: 0.2 | M23: 0.2 | N23: Biofuels | O23: Dedicated storage | P23: Aemetis CCS | Q23: North America | R23: https://www.globenewswire.com/news-release/2021/08/18/2282675/0/en/Aemetis-CCS-Drilling-Study-by-Baker-Hughes-Confirms-Feasibility-of-Sequestering-Two-Million-MT-per-Year-of-CO2-at-California-Ethanol-Plant-Sites.html | S23: https://www.aemetis.com/products/carbon-capture/ | T23: https://www.aemetis.com/products/carbon-capture/ | U23: https://www.aemetis.com/aemetis-awarded-the-first-co2-sequestration-characterization-well-permit-issued-by-the-state-of-california/ | Y23: =IF(CCUS_Projects_Database!$R23<>"",HYPERLINK(CCUS_Projects_Database!$R23,"Link 1"),"") -> Link 1 | Z23: =IF(CCUS_Projects_Database!$S23<>"",HYPERLINK(CCUS_Projects_Database!$S23,"Link 2"),"") -> Link 2 | AA23: =IF(CCUS_Projects_Database!$T23<>"",HYPERLINK(CCUS_Projects_Database!$T23,"Link 3"),"") -> Link 3 | AB23: =IF(CCUS_Projects_Database!$U23<>"",HYPERLINK(CCUS_Projects_Database!$U23,"Link 4"),"") -> Link 4 | AC23: =IF(CCUS_Projects_Database!$V23<>"",HYPERLINK(CCUS_Projects_Database!$V23,"Link 5"),"") | AD23: =IF(CCUS_Projects_Database!$W23<>"",HYPERLINK(CCUS_Projects_Database!$W23,"Link 6"),"") | AE23: =IF(CCUS_Projects_Database!$X23<>"",HYPERLINK(CCUS_Projects_Database!$X23,"Link 7"),"")
A24: Aemetis CCS Riverbank facility (CA) | B24: 16 | C24: United States | D24: Aemetis | E24: Capture | F24: 2021 | H24: 2024 | J24: Planned | L24: 0.2 | M24: 0.2 | N24: Biofuels | O24: Dedicated storage | P24: Aemetis CCS | Q24: North America | R24: https://www.globenewswire.com/news-release/2021/08/18/2282675/0/en/Aemetis-CCS-Drilling-Study-by-Baker-Hughes-Confirms-Feasibility-of-Sequestering-Two-Million-MT-per-Year-of-CO2-at-California-Ethanol-Plant-Sites.html | S24: https://www.aemetis.com/products/carbon-capture/ | T24: https://www.aemetis.com/products/carbon-capture/ | U24: https://www.aemetis.com/aemetis-awarded-the-first-co2-sequestration-characterization-well-permit-issued-by-the-state-of-california/ | Y24: =IF(CCUS_Projects_Database!$R24<>"",HYPERLINK(CCUS_Projects_Database!$R24,"Link 1"),"") -> Link 1 | Z24: =IF(CCUS_Projects_Database!$S24<>"",HYPERLINK(CCUS_Projects_Database!$S24,"Link 2"),"") -> Link 2 | AA24: =IF(CCUS_Projects_Database!$T24<>"",HYPERLINK(CCUS_Projects_Database!$T24,"Link 3"),"") -> Link 3 | AB24: =IF(CCUS_Projects_Database!$U24<>"",HYPERLINK(CCUS_Projects_Database!$U24,"Link 4"),"") -> Link 4 | AC24: =IF(CCUS_Projects_Database!$V24<>"",HYPERLINK(CCUS_Projects_Database!$V24,"Link 5"),"") | AD24: =IF(CCUS_Projects_Database!$W24<>"",HYPERLINK(CCUS_Projects_Database!$W24,"Link 6"),"") | AE24: =IF(CCUS_Projects_Database!$X24<>"",HYPERLINK(CCUS_Projects_Database!$X24,"Link 7"),"")
A25: Air Liquide hydrogen facility Rotterdam | B25: 18 | C25: Netherlands | D25: Air Liquide (build, own, operate) | E25: Capture | F25: 2012 | G25: 2023 | H25: 2026 | J25: Under construction | L25: 0.5 | M25: 0.5 | N25: Other fuel transformation | O25: Dedicated storage | P25: Porthos | Q25: Europe | R25: https://netherlandsnewslive.com/the-botlek-oil-industry-wants-2-1-billion-euros-for-co2-storage/62256/ | S25: https://www.pbl.nl/sites/default/files/downloads/pbl-2022-decarbonisation-of-the-industry-cluster-botlek-pernis-rotterdam-4946.pdf | T25: https://www.airliquide.com/group/press-releases-news/2023-12-19/air-liquide-build-world-scale-co2-capture-unit-contribute-rotterdams-industrial-basin | U25: https://www.hydrogeninsight.com/production/second-major-blue-hydrogen-project-reaches-final-investment-decision-in-rotterdam/2-1-1574743 | Y25: =IF(CCUS_Projects_Database!$R25<>"",HYPERLINK(CCUS_Projects_Database!$R25,"Link 1"),"") -> Link 1 | Z25: =IF(CCUS_Projects_Database!$S25<>"",HYPERLINK(CCUS_Projects_Database!$S25,"Link 2"),"") -> Link 2 | AA25: =IF(CCUS_Projects_Database!$T25<>"",HYPERLINK(CCUS_Projects_Database!$T25,"Link 3"),"") -> Link 3 | AB25: =IF(CCUS_Projects_Database!$U25<>"",HYPERLINK(CCUS_Projects_Database!$U25,"Link 4"),"") -> Link 4 | AC25: =IF(CCUS_Projects_Database!$V25<>"",HYPERLINK(CCUS_Projects_Database!$V25,"Link 5"),"") | AD25: =IF(CCUS_Projects_Database!$W25<>"",HYPERLINK(CCUS_Projects_Database!$W25,"Link 6"),"") | AE25: =IF(CCUS_Projects_Database!$X25<>"",HYPERLINK(CCUS_Projects_Database!$X25,"Link 7"),"")
A26: Air Liquide Shanghai Chemical Industry Park (SCIP) decarbonisation (Shanghai) | B26: 541 | C26: People's Republic of China | D26: SCIPIG (Air Liquide) | E26: Capture | F26: 2022 | H26: 2028 | J26: Planned | N26: Hydrogen or ammonia | O26: Unknown/unspecified | Q26: Other Asia Pacific | R26: https://www.airliquide.com/group/press-releases-news/2022-07-19/air-liquide-build-two-new-hydrogen-production-units-carbon-capture-technology-shanghai-chemical | S26: https://www.businesswire.com/news/home/20230718825639/en/Air-Liquide-signs-new-green-financing-for-low-carbon-hydrogen-production-in-China-aligned-with-EU-Taxonomy | Y26: =IF(CCUS_Projects_Database!$R26<>"",HYPERLINK(CCUS_Projects_Database!$R26,"Link 1"),"") -> Link 1 | Z26: =IF(CCUS_Projects_Database!$S26<>"",HYPERLINK(CCUS_Projects_Database!$S26,"Link 2"),"") -> Link 2 | AA26: =IF(CCUS_Projects_Database!$T26<>"",HYPERLINK(CCUS_Projects_Database!$T26,"Link 3"),"") | AB26: =IF(CCUS_Projects_Database!$U26<>"",HYPERLINK(CCUS_Projects_Database!$U26,"Link 4"),"") | AC26: =IF(CCUS_Projects_Database!$V26<>"",HYPERLINK(CCUS_Projects_Database!$V26,"Link 5"),"") | AD26: =IF(CCUS_Projects_Database!$W26<>"",HYPERLINK(CCUS_Projects_Database!$W26,"Link 6"),"") | AE26: =IF(CCUS_Projects_Database!$X26<>"",HYPERLINK(CCUS_Projects_Database!$X26,"Link 7"),"")
A27: Air Products for Exxonmobil Botlek Rotterdam refinery | B27: 150 | C27: Netherlands | D27: Exxonmobil, Air Products | E27: Capture | F27: 2019 | G27: 2023 | H27: 2026 | J27: Under construction | M27: 1.011 | N27: Other fuel transformation | O27: Dedicated storage | P27: Porthos | Q27: Europe | R27: https://netherlandsnewslive.com/the-botlek-oil-industry-wants-2-1-billion-euros-for-co2-storage/62256/ | S27: https://www.airproducts.com/company/news-center/2023/11/1106-air-products-blue-hydrogen-plant-europe-and-exxonmobil-long-term-agreement | T27: https://www.hydrogeninsight.com/production/largest-in-europe-air-products-announces-blue-hydrogen-plant-at-rotterdam-linked-to-dutch-offshore-ccs-network/2-1-1549667 | Y27: =IF(CCUS_Projects_Database!$R27<>"",HYPERLINK(CCUS_Projects_Database!$R27,"Link 1"),"") -> Link 1 | Z27: =IF(CCUS_Projects_Database!$S27<>"",HYPERLINK(CCUS_Projects_Database!$S27,"Link 2"),"") -> Link 2 | AA27: =IF(CCUS_Projects_Database!$T27<>"",HYPERLINK(CCUS_Projects_Database!$T27,"Link 3"),"") -> Link 3 | AB27: =IF(CCUS_Projects_Database!$U27<>"",HYPERLINK(CCUS_Projects_Database!$U27,"Link 4"),"") | AC27: =IF(CCUS_Projects_Database!$V27<>"",HYPERLINK(CCUS_Projects_Database!$V27,"Link 5"),"") | AD27: =IF(CCUS_Projects_Database!$W27<>"",HYPERLINK(CCUS_Projects_Database!$W27,"Link 6"),"") | AE27: =IF(CCUS_Projects_Database!$X27<>"",HYPERLINK(CCUS_Projects_Database!$X27,"Link 7"),"")
A28: AirCapture DACU at Nutrien Kennewick Fertilizer (WA) | B28: 21 | C28: United States | D28: AirCapture, Nutrien | E28: CCU | F28: 2022 | J28: Planned | N28: DAC | O28: Use | Q28: North America | R28: https://www.energy.gov/fecm/articles/selections-funding-opportunity-announcement-2560-direct-air-capture-combined | Y28: =IF(CCUS_Projects_Database!$R28<>"",HYPERLINK(CCUS_Projects_Database!$R28,"Link 1"),"") -> Link 1 | Z28: =IF(CCUS_Projects_Database!$S28<>"",HYPERLINK(CCUS_Projects_Database!$S28,"Link 2"),"") | AA28: =IF(CCUS_Projects_Database!$T28<>"",HYPERLINK(CCUS_Projects_Database!$T28,"Link 3"),"") | AB28: =IF(CCUS_Projects_Database!$U28<>"",HYPERLINK(CCUS_Projects_Database!$U28,"Link 4"),"") | AC28: =IF(CCUS_Projects_Database!$V28<>"",HYPERLINK(CCUS_Projects_Database!$V28,"Link 5"),"") | AD28: =IF(CCUS_Projects_Database!$W28<>"",HYPERLINK(CCUS_Projects_Database!$W28,"Link 6"),"") | AE28: =IF(CCUS_Projects_Database!$X28<>"",HYPERLINK(CCUS_Projects_Database!$X28,"Link 7"),"")
A29: AirCapture Nuclear DAC at JM Farley Nuclear (AL) | B29: 22 | C29: United States | D29: Southern Company, Battelle, AirCapture LLC | E29: Capture | F29: 2022 | J29: Planned | N29: DAC | O29: Dedicated storage | Q29: North America | R29: https://www.energy.gov/fecm/articles/selections-funding-opportunity-announcement-2560-direct-air-capture-combined | S29: https://www.power-eng.com/emissions/doe-funds-direct-air-capture-project-at-alabama-nuclear-plant/ | Y29: =IF(CCUS_Projects_Database!$R29<>"",HYPERLINK(CCUS_Projects_Database!$R29,"Link 1"),"") -> Link 1 | Z29: =IF(CCUS_Projects_Database!$S29<>"",HYPERLINK(CCUS_Projects_Database!$S29,"Link 2"),"") -> Link 2 | AA29: =IF(CCUS_Projects_Database!$T29<>"",HYPERLINK(CCUS_Projects_Database!$T29,"Link 3"),"") | AB29: =IF(CCUS_Projects_Database!$U29<>"",HYPERLINK(CCUS_Projects_Database!$U29,"Link 4"),"") | AC29: =IF(CCUS_Projects_Database!$V29<>"",HYPERLINK(CCUS_Projects_Database!$V29,"Link 5"),"") | AD29: =IF(CCUS_Projects_Database!$W29<>"",HYPERLINK(CCUS_Projects_Database!$W29,"Link 6"),"") | AE29: =IF(CCUS_Projects_Database!$X29<>"",HYPERLINK(CCUS_Projects_Database!$X29,"Link 7"),"")
A30: Airhive Alpha Lab pilot | B30: 952 | C30: Canada | D30: Airhive, Deep Sky | E30: CCU | F30: 2023 | H30: 2024 | J30: Planned | L30: 0.001 | M30: 0.001 | N30: DAC | O30: Use | Q30: North America | R30: https://airhive.earth/news/deep-sky-airhive-collab | Y30: =IF(CCUS_Projects_Database!$R30<>"",HYPERLINK(CCUS_Projects_Database!$R30,"Link 1"),"") -> Link 1 | Z30: =IF(CCUS_Projects_Database!$S30<>"",HYPERLINK(CCUS_Projects_Database!$S30,"Link 2"),"") | AA30: =IF(CCUS_Projects_Database!$T30<>"",HYPERLINK(CCUS_Projects_Database!$T30,"Link 3"),"") | AB30: =IF(CCUS_Projects_Database!$U30<>"",HYPERLINK(CCUS_Projects_Database!$U30,"Link 4"),"") | AC30: =IF(CCUS_Projects_Database!$V30<>"",HYPERLINK(CCUS_Projects_Database!$V30,"Link 5"),"") | AD30: =IF(CCUS_Projects_Database!$W30<>"",HYPERLINK(CCUS_Projects_Database!$W30,"Link 6"),"") | AE30: =IF(CCUS_Projects_Database!$X30<>"",HYPERLINK(CCUS_Projects_Database!$X30,"Link 7"),"")
A31: Aittaluoto power (Pori) | B31: 1032 | C31: Finland | D31: RenGas, Pori Energia | E31: CCU | F31: 2022 | G31: 2025 | H31: 2027 | J31: Planned | L31: 0.1 | M31: 0.1 | N31: Power and heat | O31: Use | Q31: Europe | R31: https://ren-gas.com/en/projekti/pori-2/ | Y31: =IF(CCUS_Projects_Database!$R31<>"",HYPERLINK(CCUS_Projects_Database!$R31,"Link 1"),"") -> Link 1 | Z31: =IF(CCUS_Projects_Database!$S31<>"",HYPERLINK(CCUS_Projects_Database!$S31,"Link 2"),"") | AA31: =IF(CCUS_Projects_Database!$T31<>"",HYPERLINK(CCUS_Projects_Database!$T31,"Link 3"),"") | AB31: =IF(CCUS_Projects_Database!$U31<>"",HYPERLINK(CCUS_Projects_Database!$U31,"Link 4"),"") | AC31: =IF(CCUS_Projects_Database!$V31<>"",HYPERLINK(CCUS_Projects_Database!$V31,"Link 5"),"") | AD31: =IF(CCUS_Projects_Database!$W31<>"",HYPERLINK(CCUS_Projects_Database!$W31,"Link 6"),"") | AE31: =IF(CCUS_Projects_Database!$X31<>"",HYPERLINK(CCUS_Projects_Database!$X31,"Link 7"),"")
A32: Aker CC Biomass CHP (unknown facility) | B32: 1099 | C32: Germany | D32: Aker CC, unknown company | E32: Capture | F32: 2023 | J32: Planned | L32: 0.25 | M32: 0.25 | N32: Power and heat | O32: Unknown/unspecified | Q32: Europe | R32: https://akercarboncapture.com/?cision_id=4338F917D2B89C6E | Y32: =IF(CCUS_Projects_Database!$R32<>"",HYPERLINK(CCUS_Projects_Database!$R32,"Link 1"),"") -> Link 1 | Z32: =IF(CCUS_Projects_Database!$S32<>"",HYPERLINK(CCUS_Projects_Database!$S32,"Link 2"),"") | AA32: =IF(CCUS_Projects_Database!$T32<>"",HYPERLINK(CCUS_Projects_Database!$T32,"Link 3"),"") | AB32: =IF(CCUS_Projects_Database!$U32<>"",HYPERLINK(CCUS_Projects_Database!$U32,"Link 4"),"") | AC32: =IF(CCUS_Projects_Database!$V32<>"",HYPERLINK(CCUS_Projects_Database!$V32,"Link 5"),"") | AD32: =IF(CCUS_Projects_Database!$W32<>"",HYPERLINK(CCUS_Projects_Database!$W32,"Link 6"),"") | AE32: =IF(CCUS_Projects_Database!$X32<>"",HYPERLINK(CCUS_Projects_Database!$X32,"Link 7"),"")
A33: Aker CC mineral production (unknown facilities) | B33: 920 | C33: United States | D33: Aker CC, unknown company | E33: Capture | F33: 2023 | J33: Planned | L33: 1.5 | M33: 1.5 | N33: Cement | O33: Unknown/unspecified | Q33: North America | R33: https://akercarboncapture.com/?cision_id=C8E822C2D97A90E2 | Y33: =IF(CCUS_Projects_Database!$R33<>"",HYPERLINK(CCUS_Projects_Database!$R33,"Link 1"),"") -> Link 1 | Z33: =IF(CCUS_Projects_Database!$S33<>"",HYPERLINK(CCUS_Projects_Database!$S33,"Link 2"),"") | AA33: =IF(CCUS_Projects_Database!$T33<>"",HYPERLINK(CCUS_Projects_Database!$T33,"Link 3"),"") | AB33: =IF(CCUS_Projects_Database!$U33<>"",HYPERLINK(CCUS_Projects_Database!$U33,"Link 4"),"") | AC33: =IF(CCUS_Projects_Database!$V33<>"",HYPERLINK(CCUS_Projects_Database!$V33,"Link 5"),"") | AD33: =IF(CCUS_Projects_Database!$W33<>"",HYPERLINK(CCUS_Projects_Database!$W33,"Link 6"),"") | AE33: =IF(CCUS_Projects_Database!$X33<>"",HYPERLINK(CCUS_Projects_Database!$X33,"Link 7"),"")
A34: Aker CC power plant Europe (unknown facilities) | B34: 1097 | C34: Unknown | D34: Aker CC, unknown company | E34: Capture | F34: 2023 | J34: Planned | L34: 14 | M34: 14 | N34: Power and heat | O34: Unknown/unspecified | Q34: Unknown | R34: https://akercarboncapture.com/?cision_id=42ED18602F06D910 | Y34: =IF(CCUS_Projects_Database!$R34<>"",HYPERLINK(CCUS_Projects_Database!$R34,"Link 1"),"") -> Link 1 | Z34: =IF(CCUS_Projects_Database!$S34<>"",HYPERLINK(CCUS_Projects_Database!$S34,"Link 2"),"") | AA34: =IF(CCUS_Projects_Database!$T34<>"",HYPERLINK(CCUS_Projects_Database!$T34,"Link 3"),"") | AB34: =IF(CCUS_Projects_Database!$U34<>"",HYPERLINK(CCUS_Projects_Database!$U34,"Link 4"),"") | AC34: =IF(CCUS_Projects_Database!$V34<>"",HYPERLINK(CCUS_Projects_Database!$V34,"Link 5"),"") | AD34: =IF(CCUS_Projects_Database!$W34<>"",HYPERLINK(CCUS_Projects_Database!$W34,"Link 6"),"") | AE34: =IF(CCUS_Projects_Database!$X34<>"",HYPERLINK(CCUS_Projects_Database!$X34,"Link 7"),"")
A35: Aker CC refinery (unknown facility) | B35: 1103 | C35: United States | D35: Aker CC, unknown company | E35: Capture | F35: 2023 | J35: Planned | L35: 1.2 | M35: 1.2 | N35: Other fuel transformation | O35: Unknown/unspecified | Q35: North America | Y35: =IF(CCUS_Projects_Database!$R35<>"",HYPERLINK(CCUS_Projects_Database!$R35,"Link 1"),"") | Z35: =IF(CCUS_Projects_Database!$S35<>"",HYPERLINK(CCUS_Projects_Database!$S35,"Link 2"),"") | AA35: =IF(CCUS_Projects_Database!$T35<>"",HYPERLINK(CCUS_Projects_Database!$T35,"Link 3"),"") | AB35: =IF(CCUS_Projects_Database!$U35<>"",HYPERLINK(CCUS_Projects_Database!$U35,"Link 4"),"") | AC35: =IF(CCUS_Projects_Database!$V35<>"",HYPERLINK(CCUS_Projects_Database!$V35,"Link 5"),"") | AD35: =IF(CCUS_Projects_Database!$W35<>"",HYPERLINK(CCUS_Projects_Database!$W35,"Link 6"),"") | AE35: =IF(CCUS_Projects_Database!$X35<>"",HYPERLINK(CCUS_Projects_Database!$X35,"Link 7"),"")
A36: Aker CC Swedish energy company (unknown) | B36: 1100 | C36: Sweden | D36: Aker CC, unknown company | E36: Capture | F36: 2023 | J36: Planned | L36: 0.2 | M36: 0.2 | N36: Power and heat | O36: Unknown/unspecified | Q36: Europe | Y36: =IF(CCUS_Projects_Database!$R36<>"",HYPERLINK(CCUS_Projects_Database!$R36,"Link 1"),"") | Z36: =IF(CCUS_Projects_Database!$S36<>"",HYPERLINK(CCUS_Projects_Database!$S36,"Link 2"),"") | AA36: =IF(CCUS_Projects_Database!$T36<>"",HYPERLINK(CCUS_Projects_Database!$T36,"Link 3"),"") | AB36: =IF(CCUS_Projects_Database!$U36<>"",HYPERLINK(CCUS_Projects_Database!$U36,"Link 4"),"") | AC36: =IF(CCUS_Projects_Database!$V36<>"",HYPERLINK(CCUS_Projects_Database!$V36,"Link 5"),"") | AD36: =IF(CCUS_Projects_Database!$W36<>"",HYPERLINK(CCUS_Projects_Database!$W36,"Link 6"),"") | AE36: =IF(CCUS_Projects_Database!$X36<>"",HYPERLINK(CCUS_Projects_Database!$X36,"Link 7"),"")
A37: Aker CC waste to energy Northern Europe (unknown facility) | B37: 1102 | C37: Unknown | D37: Aker CC, unknown company | E37: Capture | F37: 2024 | J37: Planned | N37: Power and heat | O37: Unknown/unspecified | Q37: Europe | R37: https://akercarboncapture.com/?cision_id=3538EFD96277831D | Y37: =IF(CCUS_Projects_Database!$R37<>"",HYPERLINK(CCUS_Projects_Database!$R37,"Link 1"),"") -> Link 1 | Z37: =IF(CCUS_Projects_Database!$S37<>"",HYPERLINK(CCUS_Projects_Database!$S37,"Link 2"),"") | AA37: =IF(CCUS_Projects_Database!$T37<>"",HYPERLINK(CCUS_Projects_Database!$T37,"Link 3"),"") | AB37: =IF(CCUS_Projects_Database!$U37<>"",HYPERLINK(CCUS_Projects_Database!$U37,"Link 4"),"") | AC37: =IF(CCUS_Projects_Database!$V37<>"",HYPERLINK(CCUS_Projects_Database!$V37,"Link 5"),"") | AD37: =IF(CCUS_Projects_Database!$W37<>"",HYPERLINK(CCUS_Projects_Database!$W37,"Link 6"),"") | AE37: =IF(CCUS_Projects_Database!$X37<>"",HYPERLINK(CCUS_Projects_Database!$X37,"Link 7"),"")
A38: Aker CC WtE e-fuels | B38: 1098 | C38: Finland | D38: Aker CC, unknown company | E38: CCU | F38: 2023 | J38: Planned | L38: 0.1 | M38: 0.1 | N38: Power and heat | O38: Use | Q38: Europe | R38: https://akercarboncapture.com/?cision_id=4676790745A256E2 | Y38: =IF(CCUS_Projects_Database!$R38<>"",HYPERLINK(CCUS_Projects_Database!$R38,"Link 1"),"") -> Link 1 | Z38: =IF(CCUS_Projects_Database!$S38<>"",HYPERLINK(CCUS_Projects_Database!$S38,"Link 2"),"") | AA38: =IF(CCUS_Projects_Database!$T38<>"",HYPERLINK(CCUS_Projects_Database!$T38,"Link 3"),"") | AB38: =IF(CCUS_Projects_Database!$U38<>"",HYPERLINK(CCUS_Projects_Database!$U38,"Link 4"),"") | AC38: =IF(CCUS_Projects_Database!$V38<>"",HYPERLINK(CCUS_Projects_Database!$V38,"Link 5"),"") | AD38: =IF(CCUS_Projects_Database!$W38<>"",HYPERLINK(CCUS_Projects_Database!$W38,"Link 6"),"") | AE38: =IF(CCUS_Projects_Database!$X38<>"",HYPERLINK(CCUS_Projects_Database!$X38,"Link 7"),"")
A39: Alaska Railbelt CCS Project (AK) | B39: 976 | C39: United States | D39: University of Alaska Fairbanks | E39: Storage | F39: 2023 | J39: Planned | N39: Storage | O39: Dedicated storage | P39: Alaska Railbelt CCS Project (AK) | Q39: North America | R39: https://www.energy.gov/fecm/project-selections-foa-2711-carbon-storage-validation-and-testing-round-2 | Y39: =IF(CCUS_Projects_Database!$R39<>"",HYPERLINK(CCUS_Projects_Database!$R39,"Link 1"),"") -> Link 1 | Z39: =IF(CCUS_Projects_Database!$S39<>"",HYPERLINK(CCUS_Projects_Database!$S39,"Link 2"),"") | AA39: =IF(CCUS_Projects_Database!$T39<>"",HYPERLINK(CCUS_Projects_Database!$T39,"Link 3"),"") | AB39: =IF(CCUS_Projects_Database!$U39<>"",HYPERLINK(CCUS_Projects_Database!$U39,"Link 4"),"") | AC39: =IF(CCUS_Projects_Database!$V39<>"",HYPERLINK(CCUS_Projects_Database!$V39,"Link 5"),"") | AD39: =IF(CCUS_Projects_Database!$W39<>"",HYPERLINK(CCUS_Projects_Database!$W39,"Link 6"),"") | AE39: =IF(CCUS_Projects_Database!$X39<>"",HYPERLINK(CCUS_Projects_Database!$X39,"Link 7"),"")
A40: Alberta Carbon Grid (ALB) phase 1 (Industrial heartland) | B40: 24 | C40: Canada | D40: Pembina Pipeline Corporation, TC Energy | E40: T&S | F40: 2021 | G40: 2025 | H40: 2027 | J40: Planned | L40: 10 | M40: 10 | N40: T&S | O40: Dedicated storage | P40: Alberta Carbon Grid (ALB) | Q40: North America | R40: https://albertacarbongrid.ca/ | S40: https://albertacarbongrid.ca/news/acg-secures-rights-to-evaluate-one-of-the-largest-carbon-storage-areas-in-alberta/ | Y40: =IF(CCUS_Projects_Database!$R40<>"",HYPERLINK(CCUS_Projects_Database!$R40,"Link 1"),"") -> Link 1 | Z40: =IF(CCUS_Projects_Database!$S40<>"",HYPERLINK(CCUS_Projects_Database!$S40,"Link 2"),"") -> Link 2 | AA40: =IF(CCUS_Projects_Database!$T40<>"",HYPERLINK(CCUS_Projects_Database!$T40,"Link 3"),"") | AB40: =IF(CCUS_Projects_Database!$U40<>"",HYPERLINK(CCUS_Projects_Database!$U40,"Link 4"),"") | AC40: =IF(CCUS_Projects_Database!$V40<>"",HYPERLINK(CCUS_Projects_Database!$V40,"Link 5"),"") | AD40: =IF(CCUS_Projects_Database!$W40<>"",HYPERLINK(CCUS_Projects_Database!$W40,"Link 6"),"") | AE40: =IF(CCUS_Projects_Database!$X40<>"",HYPERLINK(CCUS_Projects_Database!$X40,"Link 7"),"")
A41: Alberta Carbon Grid (ALB) phase 2 | B41: 492 | C41: Canada | D41: Pembina Pipeline Corporation, TC Energy | E41: T&S | F41: 2021 | J41: Planned | L41: 10 | M41: 10 | N41: T&S | O41: Dedicated storage | P41: Alberta Carbon Grid (ALB) | Q41: North America | R41: https://albertacarbongrid.ca/news/acg-secures-rights-to-evaluate-one-of-the-largest-carbon-storage-areas-in-alberta/ | Y41: =IF(CCUS_Projects_Database!$R41<>"",HYPERLINK(CCUS_Projects_Database!$R41,"Link 1"),"") -> Link 1 | Z41: =IF(CCUS_Projects_Database!$S41<>"",HYPERLINK(CCUS_Projects_Database!$S41,"Link 2"),"") | AA41: =IF(CCUS_Projects_Database!$T41<>"",HYPERLINK(CCUS_Projects_Database!$T41,"Link 3"),"") | AB41: =IF(CCUS_Projects_Database!$U41<>"",HYPERLINK(CCUS_Projects_Database!$U41,"Link 4"),"") | AC41: =IF(CCUS_Projects_Database!$V41<>"",HYPERLINK(CCUS_Projects_Database!$V41,"Link 5"),"") | AD41: =IF(CCUS_Projects_Database!$W41<>"",HYPERLINK(CCUS_Projects_Database!$W41,"Link 6"),"") | AE41: =IF(CCUS_Projects_Database!$X41<>"",HYPERLINK(CCUS_Projects_Database!$X41,"Link 7"),"")
A42: Alberta Carbon Trunk Line (ACTL) - Edmonton Connector Phase 2 | B42: 831 | C42: Canada | D42: Wolf Midstream | E42: Transport | F42: 2023 | G42: 2023 | H42: 2024 | J42: Under construction | L42: 7 | M42: 7 | N42: Transport | O42: Dedicated storage | P42: Alberta Carbon Trunk Line (ACTL) | Q42: North America | R42: https://www.newswire.ca/news-releases/wolf-midstream-to-extend-alberta-carbon-trunk-line-into-the-edmonton-region-enabling-large-scale-emissions-reduction-872102700.html | S42: https://gaspathways.com/wolf-midstream-to-extend-alberta-co2-pipeline-2209 | Y42: =IF(CCUS_Projects_Database!$R42<>"",HYPERLINK(CCUS_Projects_Database!$R42,"Link 1"),"") -> Link 1 | Z42: =IF(CCUS_Projects_Database!$S42<>"",HYPERLINK(CCUS_Projects_Database!$S42,"Link 2"),"") -> Link 2 | AA42: =IF(CCUS_Projects_Database!$T42<>"",HYPERLINK(CCUS_Projects_Database!$T42,"Link 3"),"") | AB42: =IF(CCUS_Projects_Database!$U42<>"",HYPERLINK(CCUS_Projects_Database!$U42,"Link 4"),"") | AC42: =IF(CCUS_Projects_Database!$V42<>"",HYPERLINK(CCUS_Projects_Database!$V42,"Link 5"),"") | AD42: =IF(CCUS_Projects_Database!$W42<>"",HYPERLINK(CCUS_Projects_Database!$W42,"Link 6"),"") | AE42: =IF(CCUS_Projects_Database!$X42<>"",HYPERLINK(CCUS_Projects_Database!$X42,"Link 7"),"")
A43: Alberta Carbon Trunk Line (ACTL) (ALB) | B43: 25 | C43: Canada | D43: Wolf Carbon Solutions (Wolf Midstream, Enhance Energy) | E43: Transport | F43: 2011 | G43: 2018 | H43: 2020 | J43: Operational | L43: 14.6 | M43: 14.6 | N43: Transport | O43: EOR | P43: Alberta Carbon Trunk Line (ACTL)/Enhance Clive Sequestration Facility | Q43: North America | R43: https://majorprojects.alberta.ca/details/Alberta-Carbon-Trunk-Line/622 | Y43: =IF(CCUS_Projects_Database!$R43<>"",HYPERLINK(CCUS_Projects_Database!$R43,"Link 1"),"") -> Link 1 | Z43: =IF(CCUS_Projects_Database!$S43<>"",HYPERLINK(CCUS_Projects_Database!$S43,"Link 2"),"") | AA43: =IF(CCUS_Projects_Database!$T43<>"",HYPERLINK(CCUS_Projects_Database!$T43,"Link 3"),"") | AB43: =IF(CCUS_Projects_Database!$U43<>"",HYPERLINK(CCUS_Projects_Database!$U43,"Link 4"),"") | AC43: =IF(CCUS_Projects_Database!$V43<>"",HYPERLINK(CCUS_Projects_Database!$V43,"Link 5"),"") | AD43: =IF(CCUS_Projects_Database!$W43<>"",HYPERLINK(CCUS_Projects_Database!$W43,"Link 6"),"") | AE43: =IF(CCUS_Projects_Database!$X43<>"",HYPERLINK(CCUS_Projects_Database!$X43,"Link 7"),"")
A44: Altalto | B44: 1107 | C44: United Kingdom | D44: Altalto Immingham Limited | E44: Capture | F44: 2021 | J44: Planned | N44: Biofuels | O44: Dedicated storage | P44: Northern Endurance Partnership | Q44: Europe | R44: https://www.altalto.com/2023/05/10/altalto-immingham-project-update/ | Y44: =IF(CCUS_Projects_Database!$R44<>"",HYPERLINK(CCUS_Projects_Database!$R44,"Link 1"),"") -> Link 1 | Z44: =IF(CCUS_Projects_Database!$S44<>"",HYPERLINK(CCUS_Projects_Database!$S44,"Link 2"),"") | AA44: =IF(CCUS_Projects_Database!$T44<>"",HYPERLINK(CCUS_Projects_Database!$T44,"Link 3"),"") | AB44: =IF(CCUS_Projects_Database!$U44<>"",HYPERLINK(CCUS_Projects_Database!$U44,"Link 4"),"") | AC44: =IF(CCUS_Projects_Database!$V44<>"",HYPERLINK(CCUS_Projects_Database!$V44,"Link 5"),"") | AD44: =IF(CCUS_Projects_Database!$W44<>"",HYPERLINK(CCUS_Projects_Database!$W44,"Link 6"),"") | AE44: =IF(CCUS_Projects_Database!$X44<>"",HYPERLINK(CCUS_Projects_Database!$X44,"Link 7"),"")
A45: Altera Stella Maris CCS Project Phase 2 | B45: 28 | C45: Norway | D45: Altera, Hoegh LNG, Sevan SSP (FEED), Wintershall Dea | E45: T&S | F45: 2020 | J45: Planned | K45: 2 | L45: 3 | M45: 3 | N45: T&S | O45: Dedicated storage | P45: Altera Stella Maris CCS/ Havstjerne | Q45: Europe | R45: https://alterainfra.com/what-we-do/ccs | S45: https://alterainfra.com/articles/one-step-closer-to-realising-stella-maris-ccs | T45: https://www.regjeringen.no/en/aktuelt/award-of-two-new-licences-for-co2-storage-on-the-norwegian-continental-shelf/id2970248/ | U45: https://alterainfra.com/what-we-do/ccs | V45: https://alterainfra.com/articles/one-step-closer-to-realising-stella-maris-ccs | Y45: =IF(CCUS_Projects_Database!$R45<>"",HYPERLINK(CCUS_Projects_Database!$R45,"Link 1"),"") -> Link 1 | Z45: =IF(CCUS_Projects_Database!$S45<>"",HYPERLINK(CCUS_Projects_Database!$S45,"Link 2"),"") -> Link 2 | AA45: =IF(CCUS_Projects_Database!$T45<>"",HYPERLINK(CCUS_Projects_Database!$T45,"Link 3"),"") -> Link 3 | AB45: =IF(CCUS_Projects_Database!$U45<>"",HYPERLINK(CCUS_Projects_Database!$U45,"Link 4"),"") -> Link 4 | AC45: =IF(CCUS_Projects_Database!$V45<>"",HYPERLINK(CCUS_Projects_Database!$V45,"Link 5"),"") -> Link 5 | AD45: =IF(CCUS_Projects_Database!$W45<>"",HYPERLINK(CCUS_Projects_Database!$W45,"Link 6"),"") | AE45: =IF(CCUS_Projects_Database!$X45<>"",HYPERLINK(CCUS_Projects_Database!$X45,"Link 7"),"")
A46: Aluminium Bahrain MHI capture | B46: 29 | C46: Bahrain | D46: Aluminium Bahrain (Alba), Mitsubishi HI (Feasibility/tech) | E46: Capture | F46: 2022 | J46: Planned | N46: Other industry | O46: Unknown/unspecified | Q46: Middle East | R46: https://www.reuters.com/business/sustainable-business/aluminium-bahrain-mitsubishi-heavy-industries-sign-mou-carbon-capture-2022-01-19/ | Y46: =IF(CCUS_Projects_Database!$R46<>"",HYPERLINK(CCUS_Projects_Database!$R46,"Link 1"),"") -> Link 1 | Z46: =IF(CCUS_Projects_Database!$S46<>"",HYPERLINK(CCUS_Projects_Database!$S46,"Link 2"),"") | AA46: =IF(CCUS_Projects_Database!$T46<>"",HYPERLINK(CCUS_Projects_Database!$T46,"Link 3"),"") | AB46: =IF(CCUS_Projects_Database!$U46<>"",HYPERLINK(CCUS_Projects_Database!$U46,"Link 4"),"") | AC46: =IF(CCUS_Projects_Database!$V46<>"",HYPERLINK(CCUS_Projects_Database!$V46,"Link 5"),"") | AD46: =IF(CCUS_Projects_Database!$W46<>"",HYPERLINK(CCUS_Projects_Database!$W46,"Link 6"),"") | AE46: =IF(CCUS_Projects_Database!$X46<>"",HYPERLINK(CCUS_Projects_Database!$X46,"Link 7"),"")
A47: Aluminium Dunkerque feasibility study | B47: 809 | C47: France | D47: EDF, Aluminium Dunkerque, Trimet, Rio Tinto and Fives | E47: Capture | F47: 2021 | J47: Planned | L47: 0.24 | M47: 0.24 | N47: Other industry | O47: Unknown/unspecified | Q47: Europe | R47: https://papers.ssrn.com/sol3/papers.cfm?abstract_id=4271839 | S47: https://www.usinenouvelle.com/article/nous-lancons-un-projet-de-capture-de-co2-pour-l-aluminium-primaire-annonce-guillaume-de-goys-president-d-aluminium-france.N1049874 | Y47: =IF(CCUS_Projects_Database!$R47<>"",HYPERLINK(CCUS_Projects_Database!$R47,"Link 1"),"") -> Link 1 | Z47: =IF(CCUS_Projects_Database!$S47<>"",HYPERLINK(CCUS_Projects_Database!$S47,"Link 2"),"") -> Link 2 | AA47: =IF(CCUS_Projects_Database!$T47<>"",HYPERLINK(CCUS_Projects_Database!$T47,"Link 3"),"") | AB47: =IF(CCUS_Projects_Database!$U47<>"",HYPERLINK(CCUS_Projects_Database!$U47,"Link 4"),"") | AC47: =IF(CCUS_Projects_Database!$V47<>"",HYPERLINK(CCUS_Projects_Database!$V47,"Link 5"),"") | AD47: =IF(CCUS_Projects_Database!$W47<>"",HYPERLINK(CCUS_Projects_Database!$W47,"Link 6"),"") | AE47: =IF(CCUS_Projects_Database!$X47<>"",HYPERLINK(CCUS_Projects_Database!$X47,"Link 7"),"")
A48: Amager Bakke/Amager Resource Centre (ARC) | B48: 89 | C48: Denmark | D48: ARC, Babcock & Wilcox, Copenhagen Port | E48: Capture | F48: 2020 | H48: 2025 | J48: Planned | L48: 0.5 | M48: 0.5 | N48: Power and heat | O48: Dedicated storage | Q48: Europe | R48: https://www.maritime-executive.com/article/copenhagen-port-participates-in-carbon-capture-and-storage-project | S48: https://www.energy-supply.dk/procurement/view/138997/market_dialogue_project_climaid_copenhagen_delivery_and_commissioning_of_a_carbon_capture_unit_at_arc_premises | T48: https://a-r-c.dk/klima-og-miljo/co2-fangst/ | U48: https://a-r-c.dk/about-arc/carbon-capture/ | Y48: =IF(CCUS_Projects_Database!$R48<>"",HYPERLINK(CCUS_Projects_Database!$R48,"Link 1"),"") -> Link 1 | Z48: =IF(CCUS_Projects_Database!$S48<>"",HYPERLINK(CCUS_Projects_Database!$S48,"Link 2"),"") -> Link 2 | AA48: =IF(CCUS_Projects_Database!$T48<>"",HYPERLINK(CCUS_Projects_Database!$T48,"Link 3"),"") -> Link 3 | AB48: =IF(CCUS_Projects_Database!$U48<>"",HYPERLINK(CCUS_Projects_Database!$U48,"Link 4"),"") -> Link 4 | AC48: =IF(CCUS_Projects_Database!$V48<>"",HYPERLINK(CCUS_Projects_Database!$V48,"Link 5"),"") | AD48: =IF(CCUS_Projects_Database!$W48<>"",HYPERLINK(CCUS_Projects_Database!$W48,"Link 6"),"") | AE48: =IF(CCUS_Projects_Database!$X48<>"",HYPERLINK(CCUS_Projects_Database!$X48,"Link 7"),"")
A49: ANRAV-CCUS (Devnya plant) | B49: 560 | C49: Bulgaria | D49: Heidelberg Materials, Petroceltic | E49: Full chain | F49: 2022 | H49: 2028 | J49: Planned | K49: 1 | L49: 0.8 | M49: 0.8 | N49: Cement | O49: Dedicated storage | Q49: Europe | R49: https://www.heidelbergmaterials.com/en/pr-12-07-2022 | S49: https://www.heidelbergmaterials.com/en/pr-2023-01-20 | Y49: =IF(CCUS_Projects_Database!$R49<>"",HYPERLINK(CCUS_Projects_Database!$R49,"Link 1"),"") -> Link 1 | Z49: =IF(CCUS_Projects_Database!$S49<>"",HYPERLINK(CCUS_Projects_Database!$S49,"Link 2"),"") -> Link 2 | AA49: =IF(CCUS_Projects_Database!$T49<>"",HYPERLINK(CCUS_Projects_Database!$T49,"Link 3"),"") | AB49: =IF(CCUS_Projects_Database!$U49<>"",HYPERLINK(CCUS_Projects_Database!$U49,"Link 4"),"") | AC49: =IF(CCUS_Projects_Database!$V49<>"",HYPERLINK(CCUS_Projects_Database!$V49,"Link 5"),"") | AD49: =IF(CCUS_Projects_Database!$W49<>"",HYPERLINK(CCUS_Projects_Database!$W49,"Link 6"),"") | AE49: =IF(CCUS_Projects_Database!$X49<>"",HYPERLINK(CCUS_Projects_Database!$X49,"Link 7"),"")
A50: Antwerp@C CO2 Export Hub phase 1 | B50: 31 | C50: Belgium | D50: Air Liquide, BASF, Borealis, ExxonMobil, INEOS, TotalEnergies, Fluxys and the Port of Antwerp | E50: Transport | F50: 2019 | G50: 2024 | H50: 2027 | J50: Planned | K50: 1 | L50: 2.5 | M50: 2.5 | N50: Transport | O50: Dedicated storage | P50: Antwerp@C | Q50: Europe | R50: https://newsroom.portofantwerpbruges.com/the-antwerpc-project-takes-a-major-next-step-towards-halving-co2-footprint# | S50: https://www.airliquide.com/group/press-releases-news/2022-12-12/air-liquide-fluxys-belgium-and-port-antwerp-bruges-awarded-eu-funding-building-antwerpc-co2-export | T50: https://energy.ec.europa.eu/news/connecting-europe-facility-over-eu-600-million-energy-infrastructure-support-european-green-deal-and-2022-12-08_en | U50: https://cinea.ec.europa.eu/news-events/news/cef-energy-antwerpc-co2-export-hub-receives-1446-million-eu-funding-co2-capture-infrastructure-2023-06-26_en | Y50: =IF(CCUS_Projects_Database!$R50<>"",HYPERLINK(CCUS_Projects_Database!$R50,"Link 1"),"") -> Link 1 | Z50: =IF(CCUS_Projects_Database!$S50<>"",HYPERLINK(CCUS_Projects_Database!$S50,"Link 2"),"") -> Link 2 | AA50: =IF(CCUS_Projects_Database!$T50<>"",HYPERLINK(CCUS_Projects_Database!$T50,"Link 3"),"") -> Link 3 | AB50: =IF(CCUS_Projects_Database!$U50<>"",HYPERLINK(CCUS_Projects_Database!$U50,"Link 4"),"") -> Link 4 | AC50: =IF(CCUS_Projects_Database!$V50<>"",HYPERLINK(CCUS_Projects_Database!$V50,"Link 5"),"") | AD50: =IF(CCUS_Projects_Database!$W50<>"",HYPERLINK(CCUS_Projects_Database!$W50,"Link 6"),"") | AE50: =IF(CCUS_Projects_Database!$X50<>"",HYPERLINK(CCUS_Projects_Database!$X50,"Link 7"),"")
A51: Antwerp@C CO2 Export Hub phase 2 | B51: 585 | C51: Belgium | D51: Air Liquide, BASF, Borealis, ExxonMobil, INEOS, TotalEnergies, Fluxys and the Port of Antwerp | E51: Transport | F51: 2019 | G51: 2024 | H51: 2030 | J51: Planned | K51: 2 | L51: 7.5 | M51: 7.5 | N51: Transport | O51: Dedicated storage | P51: Antwerp@C | Q51: Europe | Y51: =IF(CCUS_Projects_Database!$R51<>"",HYPERLINK(CCUS_Projects_Database!$R51,"Link 1"),"") | Z51: =IF(CCUS_Projects_Database!$S51<>"",HYPERLINK(CCUS_Projects_Database!$S51,"Link 2"),"") | AA51: =IF(CCUS_Projects_Database!$T51<>"",HYPERLINK(CCUS_Projects_Database!$T51,"Link 3"),"") | AB51: =IF(CCUS_Projects_Database!$U51<>"",HYPERLINK(CCUS_Projects_Database!$U51,"Link 4"),"") | AC51: =IF(CCUS_Projects_Database!$V51<>"",HYPERLINK(CCUS_Projects_Database!$V51,"Link 5"),"") | AD51: =IF(CCUS_Projects_Database!$W51<>"",HYPERLINK(CCUS_Projects_Database!$W51,"Link 6"),"") | AE51: =IF(CCUS_Projects_Database!$X51<>"",HYPERLINK(CCUS_Projects_Database!$X51,"Link 7"),"")
A52: Appalachian basin storage MoU (OH, PA, WV) | B52: 1010 | C52: United States | D52: Battelle, Equinor | E52: Storage | F52: 2022 | J52: Planned | N52: Storage | O52: Dedicated storage | P52: CO2NNECTION Central Appalachian Basin hub/Appalachian basin storage MoU (OH, PA, WV) | Q52: North America | R52: https://www.equinor.com/news/us/explores-appalachian-basin-carbon-capture-storage-potential | S52: https://h2-tech.com/news/2023/09-2023/fidelis-new-energy-selects-battelle-carbon-services-to-support-the-mountaineer-gigasystem-hydrogen-project/ | Y52: =IF(CCUS_Projects_Database!$R52<>"",HYPERLINK(CCUS_Projects_Database!$R52,"Link 1"),"") -> Link 1 | Z52: =IF(CCUS_Projects_Database!$S52<>"",HYPERLINK(CCUS_Projects_Database!$S52,"Link 2"),"") -> Link 2 | AA52: =IF(CCUS_Projects_Database!$T52<>"",HYPERLINK(CCUS_Projects_Database!$T52,"Link 3"),"") | AB52: =IF(CCUS_Projects_Database!$U52<>"",HYPERLINK(CCUS_Projects_Database!$U52,"Link 4"),"") | AC52: =IF(CCUS_Projects_Database!$V52<>"",HYPERLINK(CCUS_Projects_Database!$V52,"Link 5"),"") | AD52: =IF(CCUS_Projects_Database!$W52<>"",HYPERLINK(CCUS_Projects_Database!$W52,"Link 6"),"") | AE52: =IF(CCUS_Projects_Database!$X52<>"",HYPERLINK(CCUS_Projects_Database!$X52,"Link 7"),"")
A53: Aramis CCS storage phase 1 | B53: 32 | C53: Netherlands | D53: TotalEnergies, Shell, EBN, Gasunie, | E53: Storage | F53: 2019 | G53: 2025 | H53: 2029 | J53: Planned | K53: 1 | L53: 7.7 | M53: 7.7 | N53: Storage | O53: Dedicated storage | P53: Aramis CCS | Q53: Europe | R53: https://www.frontiersin.org/articles/10.3389/fenrg.2021.644796/full | S53: https://www.aramis-ccs.com/faq | T53: https://ec.europa.eu/eusurvey/runner/Consultation_PCIcandidates_CO2networks | U53: https://www.staten-generaal.nl/9370000/1/j4nvgs5kjg27kof_j9vvkfvj6b325az/vlutrvd2g2y4 | V53: https://energy.ec.europa.eu/news/connecting-europe-facility-nearly-eu600-million-energy-infrastructure-contributing-decarbonisation-2023-12-08_en | Y53: =IF(CCUS_Projects_Database!$R53<>"",HYPERLINK(CCUS_Projects_Database!$R53,"Link 1"),"") -> Link 1 | Z53: =IF(CCUS_Projects_Database!$S53<>"",HYPERLINK(CCUS_Projects_Database!$S53,"Link 2"),"") -> Link 2 | AA53: =IF(CCUS_Projects_Database!$T53<>"",HYPERLINK(CCUS_Projects_Database!$T53,"Link 3"),"") -> Link 3 | AB53: =IF(CCUS_Projects_Database!$U53<>"",HYPERLINK(CCUS_Projects_Database!$U53,"Link 4"),"") -> Link 4 | AC53: =IF(CCUS_Projects_Database!$V53<>"",HYPERLINK(CCUS_Projects_Database!$V53,"Link 5"),"") -> Link 5 | AD53: =IF(CCUS_Projects_Database!$W53<>"",HYPERLINK(CCUS_Projects_Database!$W53,"Link 6"),"") | AE53: =IF(CCUS_Projects_Database!$X53<>"",HYPERLINK(CCUS_Projects_Database!$X53,"Link 7"),"")
A54: Aramis CCS storage phase 2 | B54: 33 | C54: Netherlands | D54: TotalEnergies, Shell, EBN, Gasunie | E54: Storage | F54: 2019 | H54: 2030 | J54: Planned | K54: 2 | L54: 3.1 | M54: 3.1 | N54: Storage | O54: Dedicated storage | P54: Aramis CCS | Q54: Europe | R54: https://www.frontiersin.org/articles/10.3389/fenrg.2021.644796/full | S54: https://ec.europa.eu/eusurvey/runner/Consultation_PCIcandidates_CO2networks | T54: https://energy.ec.europa.eu/news/connecting-europe-facility-nearly-eu600-million-energy-infrastructure-contributing-decarbonisation-2023-12-08_en | Y54: =IF(CCUS_Projects_Database!$R54<>"",HYPERLINK(CCUS_Projects_Database!$R54,"Link 1"),"") -> Link 1 | Z54: =IF(CCUS_Projects_Database!$S54<>"",HYPERLINK(CCUS_Projects_Database!$S54,"Link 2"),"") -> Link 2 | AA54: =IF(CCUS_Projects_Database!$T54<>"",HYPERLINK(CCUS_Projects_Database!$T54,"Link 3"),"") -> Link 3 | AB54: =IF(CCUS_Projects_Database!$U54<>"",HYPERLINK(CCUS_Projects_Database!$U54,"Link 4"),"") | AC54: =IF(CCUS_Projects_Database!$V54<>"",HYPERLINK(CCUS_Projects_Database!$V54,"Link 5"),"") | AD54: =IF(CCUS_Projects_Database!$W54<>"",HYPERLINK(CCUS_Projects_Database!$W54,"Link 6"),"") | AE54: =IF(CCUS_Projects_Database!$X54<>"",HYPERLINK(CCUS_Projects_Database!$X54,"Link 7"),"")
A55: Aramis CCS transport phase 1 | B55: 19 | C55: Netherlands | D55: TotalEnergies, Shell, EBN, Gasunie, | E55: Transport | F55: 2019 | G55: 2025 | H55: 2029 | J55: Planned | K55: 1 | L55: 22 | M55: 22 | N55: Transport | O55: Dedicated storage | P55: Aramis CCS | Q55: Europe | R55: https://www.frontiersin.org/articles/10.3389/fenrg.2021.644796/full | S55: https://www.aramis-ccs.com/faq | T55: https://ec.europa.eu/eusurvey/runner/Consultation_PCIcandidates_CO2networks | U55: https://www.staten-generaal.nl/9370000/1/j4nvgs5kjg27kof_j9vvkfvj6b325az/vlutrvd2g2y4 | V55: https://energy.ec.europa.eu/news/connecting-europe-facility-nearly-eu600-million-energy-infrastructure-contributing-decarbonisation-2023-12-08_en | Y55: =IF(CCUS_Projects_Database!$R55<>"",HYPERLINK(CCUS_Projects_Database!$R55,"Link 1"),"") -> Link 1 | Z55: =IF(CCUS_Projects_Database!$S55<>"",HYPERLINK(CCUS_Projects_Database!$S55,"Link 2"),"") -> Link 2 | AA55: =IF(CCUS_Projects_Database!$T55<>"",HYPERLINK(CCUS_Projects_Database!$T55,"Link 3"),"") -> Link 3 | AB55: =IF(CCUS_Projects_Database!$U55<>"",HYPERLINK(CCUS_Projects_Database!$U55,"Link 4"),"") -> Link 4 | AC55: =IF(CCUS_Projects_Database!$V55<>"",HYPERLINK(CCUS_Projects_Database!$V55,"Link 5"),"") -> Link 5 | AD55: =IF(CCUS_Projects_Database!$W55<>"",HYPERLINK(CCUS_Projects_Database!$W55,"Link 6"),"") | AE55: =IF(CCUS_Projects_Database!$X55<>"",HYPERLINK(CCUS_Projects_Database!$X55,"Link 7"),"")
A56: Arcelor LanzaTech Carbalyst (Steelanol) Ghent | B56: 34 | C56: Belgium | D56: ArcelorMittal, LanzaTech, Primetals Technologies, E4tech | E56: CCU | F56: 2011 | G56: 2015 | H56: 2022 | J56: Operational | L56: 0.125 | M56: 0.125 | N56: Iron and steel | O56: Use | Q56: Europe | R56: http://www.steelanol.eu/en | S56: https://corporate.arcelormittal.com/climate-action/decarbonisation-technologies/carbalyst-capturing-and-re-using-our-carbon-rich-waste-gases-to-make-valuable-chemical-products | T56: https://www.eib.org/en/projects/pipelines/all/20170622 | U56: https://www.globenewswire.com/news-release/2022/12/08/2569976/0/en/ArcelorMittal-S-A-ArcelorMittal-inaugurates-flagship-carbon-capture-and-utilisation-project-at-its-steel-plant-in-Ghent-Belgium.html | Y56: =IF(CCUS_Projects_Database!$R56<>"",HYPERLINK(CCUS_Projects_Database!$R56,"Link 1"),"") -> Link 1 | Z56: =IF(CCUS_Projects_Database!$S56<>"",HYPERLINK(CCUS_Projects_Database!$S56,"Link 2"),"") -> Link 2 | AA56: =IF(CCUS_Projects_Database!$T56<>"",HYPERLINK(CCUS_Projects_Database!$T56,"Link 3"),"") -> Link 3 | AB56: =IF(CCUS_Projects_Database!$U56<>"",HYPERLINK(CCUS_Projects_Database!$U56,"Link 4"),"") -> Link 4 | AC56: =IF(CCUS_Projects_Database!$V56<>"",HYPERLINK(CCUS_Projects_Database!$V56,"Link 5"),"") | AD56: =IF(CCUS_Projects_Database!$W56<>"",HYPERLINK(CCUS_Projects_Database!$W56,"Link 6"),"") | AE56: =IF(CCUS_Projects_Database!$X56<>"",HYPERLINK(CCUS_Projects_Database!$X56,"Link 7"),"")
A57: Arcelor Mittal Air Liquide Low-carbon steel (phase 2?) | B57: 582 | C57: France | D57: Arcelor Mittal, Air Liquide | E57: Capture | F57: 2020 | J57: Planned | K57: 2 | L57: 1.925 | M57: 1 | N57: Iron and steel | O57: Dedicated storage | Q57: Europe | R57: https://corporate.arcelormittal.com/media/press-releases/arcelormittal-accelerates-its-decarbonisation-with-a-1-7-billion-investment-programme-in-france-supported-by-the-french-government | Y57: =IF(CCUS_Projects_Database!$R57<>"",HYPERLINK(CCUS_Projects_Database!$R57,"Link 1"),"") -> Link 1 | Z57: =IF(CCUS_Projects_Database!$S57<>"",HYPERLINK(CCUS_Projects_Database!$S57,"Link 2"),"") | AA57: =IF(CCUS_Projects_Database!$T57<>"",HYPERLINK(CCUS_Projects_Database!$T57,"Link 3"),"") | AB57: =IF(CCUS_Projects_Database!$U57<>"",HYPERLINK(CCUS_Projects_Database!$U57,"Link 4"),"") | AC57: =IF(CCUS_Projects_Database!$V57<>"",HYPERLINK(CCUS_Projects_Database!$V57,"Link 5"),"") | AD57: =IF(CCUS_Projects_Database!$W57<>"",HYPERLINK(CCUS_Projects_Database!$W57,"Link 6"),"") | AE57: =IF(CCUS_Projects_Database!$X57<>"",HYPERLINK(CCUS_Projects_Database!$X57,"Link 7"),"")
A58: ARGO waste-to-energy plant | B58: 729 | C58: Denmark | D58: ARGO | E58: Capture | F58: 2021 | H58: 2030 | J58: Planned | N58: Power and heat | O58: Unknown/unspecified | Q58: Europe | R58: https://www.c4cph.dk/ | Y58: =IF(CCUS_Projects_Database!$R58<>"",HYPERLINK(CCUS_Projects_Database!$R58,"Link 1"),"") -> Link 1 | Z58: =IF(CCUS_Projects_Database!$S58<>"",HYPERLINK(CCUS_Projects_Database!$S58,"Link 2"),"") | AA58: =IF(CCUS_Projects_Database!$T58<>"",HYPERLINK(CCUS_Projects_Database!$T58,"Link 3"),"") | AB58: =IF(CCUS_Projects_Database!$U58<>"",HYPERLINK(CCUS_Projects_Database!$U58,"Link 4"),"") | AC58: =IF(CCUS_Projects_Database!$V58<>"",HYPERLINK(CCUS_Projects_Database!$V58,"Link 5"),"") | AD58: =IF(CCUS_Projects_Database!$W58<>"",HYPERLINK(CCUS_Projects_Database!$W58,"Link 6"),"") | AE58: =IF(CCUS_Projects_Database!$X58<>"",HYPERLINK(CCUS_Projects_Database!$X58,"Link 7"),"")
A59: Aries (LA) | B59: 881 | C59: United States | D59: ExxonMobil (formerly Denbury carbon solutions) | E59: Storage | F59: 2022 | H59: 2026 | J59: Planned | L59: 15 | M59: 10 | N59: Storage | O59: Unknown/unspecified | Q59: North America | R59: https://www.denbury.com/operations/carbon-solutions/carbon-sequestration/ | S59: https://s201.q4cdn.com/317576541/files/doc_presentation/2023/02/DEN-March-Presentation-vFINAL.pdf | Y59: =IF(CCUS_Projects_Database!$R59<>"",HYPERLINK(CCUS_Projects_Database!$R59,"Link 1"),"") -> Link 1 | Z59: =IF(CCUS_Projects_Database!$S59<>"",HYPERLINK(CCUS_Projects_Database!$S59,"Link 2"),"") -> Link 2 | AA59: =IF(CCUS_Projects_Database!$T59<>"",HYPERLINK(CCUS_Projects_Database!$T59,"Link 3"),"") | AB59: =IF(CCUS_Projects_Database!$U59<>"",HYPERLINK(CCUS_Projects_Database!$U59,"Link 4"),"") | AC59: =IF(CCUS_Projects_Database!$V59<>"",HYPERLINK(CCUS_Projects_Database!$V59,"Link 5"),"") | AD59: =IF(CCUS_Projects_Database!$W59<>"",HYPERLINK(CCUS_Projects_Database!$W59,"Link 6"),"") | AE59: =IF(CCUS_Projects_Database!$X59<>"",HYPERLINK(CCUS_Projects_Database!$X59,"Link 7"),"")
A60: Arkalon CO2 Compression Facility (KS) | B60: 35 | C60: United States | D60: Conestoga Energy | E60: Full chain | H60: 2009 | J60: Operational | L60: 0.25 | M60: 0.31 | N60: Biofuels | O60: EOR | Q60: North America | R60: https://www.energy.gov/sites/prod/files/2017/12/f46/jordan_bioeconomy_2017.pdf | S60: https://www.netl.doe.gov/sites/default/files/2018-11/Farnsworth-Unit-Project.pdf | Y60: =IF(CCUS_Projects_Database!$R60<>"",HYPERLINK(CCUS_Projects_Database!$R60,"Link 1"),"") -> Link 1 | Z60: =IF(CCUS_Projects_Database!$S60<>"",HYPERLINK(CCUS_Projects_Database!$S60,"Link 2"),"") -> Link 2 | AA60: =IF(CCUS_Projects_Database!$T60<>"",HYPERLINK(CCUS_Projects_Database!$T60,"Link 3"),"") | AB60: =IF(CCUS_Projects_Database!$U60<>"",HYPERLINK(CCUS_Projects_Database!$U60,"Link 4"),"") | AC60: =IF(CCUS_Projects_Database!$V60<>"",HYPERLINK(CCUS_Projects_Database!$V60,"Link 5"),"") | AD60: =IF(CCUS_Projects_Database!$W60<>"",HYPERLINK(CCUS_Projects_Database!$W60,"Link 6"),"") | AE60: =IF(CCUS_Projects_Database!$X60<>"",HYPERLINK(CCUS_Projects_Database!$X60,"Link 7"),"")
A61: Arthit offshore gas field CCS | B61: 36 | C61: Thailand | D61: PTTEP, Honeywell (tech and FEED) | E61: Full chain | F61: 2021 | H61: 2027 | J61: Planned | N61: Natural gas processing/LNG | O61: Dedicated storage | Q61: Other Asia Pacific | R61: https://www.pttep.com/en/Newsandnmedia/Mediacorner/Pressreleases/Pttep-Initiates-Thailand-First-Ccs-Project-Pushing-Towards-Net-Zero-Green-House-Gas-Emissions.aspx | S61: https://en.prnasia.com/releases/apac/honeywell-provides-carbon-capture-technology-for-pttep-391078.shtml | T61: https://www.pttep.com/en/Sustainability/Carbon-Capture-And-Storage.aspx?mode=print | Y61: =IF(CCUS_Projects_Database!$R61<>"",HYPERLINK(CCUS_Projects_Database!$R61,"Link 1"),"") -> Link 1 | Z61: =IF(CCUS_Projects_Database!$S61<>"",HYPERLINK(CCUS_Projects_Database!$S61,"Link 2"),"") -> Link 2 | AA61: =IF(CCUS_Projects_Database!$T61<>"",HYPERLINK(CCUS_Projects_Database!$T61,"Link 3"),"") -> Link 3 | AB61: =IF(CCUS_Projects_Database!$U61<>"",HYPERLINK(CCUS_Projects_Database!$U61,"Link 4"),"") | AC61: =IF(CCUS_Projects_Database!$V61<>"",HYPERLINK(CCUS_Projects_Database!$V61,"Link 5"),"") | AD61: =IF(CCUS_Projects_Database!$W61<>"",HYPERLINK(CCUS_Projects_Database!$W61,"Link 6"),"") | AE61: =IF(CCUS_Projects_Database!$X61<>"",HYPERLINK(CCUS_Projects_Database!$X61,"Link 7"),"")
A62: Arun CCS | B62: 37 | C62: Indonesia | D62: Carbon Aceh, PEMA (JV) | E62: Storage | F62: 2022 | H62: 2029 | J62: Planned | N62: Storage | O62: Dedicated storage | P62: Arun CCS | Q62: Other Asia Pacific | R62: https://www.upstreamonline.com/energy-transition/reinvigorating-indonesian-giant-as-ccs-project/2-1-1190849 | S62: https://www.carbonaceh.com/press-release-1 | T62: https://acnf.jp/program/file/presentation/7_Panelist_MEMR-IDN.pdf | Y62: =IF(CCUS_Projects_Database!$R62<>"",HYPERLINK(CCUS_Projects_Database!$R62,"Link 1"),"") -> Link 1 | Z62: =IF(CCUS_Projects_Database!$S62<>"",HYPERLINK(CCUS_Projects_Database!$S62,"Link 2"),"") -> Link 2 | AA62: =IF(CCUS_Projects_Database!$T62<>"",HYPERLINK(CCUS_Projects_Database!$T62,"Link 3"),"") -> Link 3 | AB62: =IF(CCUS_Projects_Database!$U62<>"",HYPERLINK(CCUS_Projects_Database!$U62,"Link 4"),"") | AC62: =IF(CCUS_Projects_Database!$V62<>"",HYPERLINK(CCUS_Projects_Database!$V62,"Link 5"),"") | AD62: =IF(CCUS_Projects_Database!$W62<>"",HYPERLINK(CCUS_Projects_Database!$W62,"Link 6"),"") | AE62: =IF(CCUS_Projects_Database!$X62<>"",HYPERLINK(CCUS_Projects_Database!$X62,"Link 7"),"")
A63: Ascension Clean Energy (ACE) complex (LA) | B63: 484 | C63: United States | D63: Clean Hydrogen Works (Joint venture between Denbury Carbon Solutions (ExxonMobil) (T&S), Hafnia (ammonia export), MOL (shipping)) | E63: Capture | F63: 2022 | G63: 2024 | H63: 2027 | J63: Planned | L63: 12 | M63: 12 | N63: Hydrogen or ammonia | O63: Dedicated storage | P63: Denbury Green pipeline /Gemini (LA) | Q63: North America | R63: https://www.cleanhydrogenworks.com/_files/ugd/9b794f_71f2bbea67dc4ebb8ab789194a19132a.pdf | Y63: =IF(CCUS_Projects_Database!$R63<>"",HYPERLINK(CCUS_Projects_Database!$R63,"Link 1"),"") -> Link 1 | Z63: =IF(CCUS_Projects_Database!$S63<>"",HYPERLINK(CCUS_Projects_Database!$S63,"Link 2"),"") | AA63: =IF(CCUS_Projects_Database!$T63<>"",HYPERLINK(CCUS_Projects_Database!$T63,"Link 3"),"") | AB63: =IF(CCUS_Projects_Database!$U63<>"",HYPERLINK(CCUS_Projects_Database!$U63,"Link 4"),"") | AC63: =IF(CCUS_Projects_Database!$V63<>"",HYPERLINK(CCUS_Projects_Database!$V63,"Link 5"),"") | AD63: =IF(CCUS_Projects_Database!$W63<>"",HYPERLINK(CCUS_Projects_Database!$W63,"Link 6"),"") | AE63: =IF(CCUS_Projects_Database!$X63<>"",HYPERLINK(CCUS_Projects_Database!$X63,"Link 7"),"")
A64: Ash Grove Cement Foreman Plant (AR) | B64: 1129 | C64: United States | D64: Southern States Energy Board, DOE Office of Clean Energy Demonstrations | E64: Full chain | F64: 2023 | J64: Planned | L64: 1.4 | M64: 1.4 | N64: Cement | O64: Dedicated storage | Q64: North America | R64: https://www.energy.gov/oced/carbon-capture-demonstration-projects-program-front-end-engineering-design-feed-studies | Y64: =IF(CCUS_Projects_Database!$R64<>"",HYPERLINK(CCUS_Projects_Database!$R64,"Link 1"),"") -> Link 1 | Z64: =IF(CCUS_Projects_Database!$S64<>"",HYPERLINK(CCUS_Projects_Database!$S64,"Link 2"),"") | AA64: =IF(CCUS_Projects_Database!$T64<>"",HYPERLINK(CCUS_Projects_Database!$T64,"Link 3"),"") | AB64: =IF(CCUS_Projects_Database!$U64<>"",HYPERLINK(CCUS_Projects_Database!$U64,"Link 4"),"") | AC64: =IF(CCUS_Projects_Database!$V64<>"",HYPERLINK(CCUS_Projects_Database!$V64,"Link 5"),"") | AD64: =IF(CCUS_Projects_Database!$W64<>"",HYPERLINK(CCUS_Projects_Database!$W64,"Link 6"),"") | AE64: =IF(CCUS_Projects_Database!$X64<>"",HYPERLINK(CCUS_Projects_Database!$X64,"Link 7"),"")
A65: Asnæs Power Station | B65: 756 | C65: Denmark | D65: Orsted, Aker CC (tech), NCC (construction) | E65: Capture | F65: 2022 | G65: 2023 | H65: 2026 | J65: Under construction | L65: 0.28 | M65: 0.28 | N65: Power and heat | O65: Dedicated storage | P65: Northern Lights | Q65: Europe | R65: https://orsted.com/en/media/newsroom/news/2023/05/20230515676011 | S65: https://www.bioenergy-news.com/news/orsted-bids-danish-biomass-fired-cogeneration-plants-into-carbon-capture-tender/ | T65: https://orsted.com/en/media/newsroom/news/2023/12/oersted-begins-construction-of-denmarks-first-carb-13757543 | U65: https://news.cision.com/ncc/r/ncc-contracted-by-orsted-to-construct-carbon-capture-plant-in-denmark,c3906317 | Y65: =IF(CCUS_Projects_Database!$R65<>"",HYPERLINK(CCUS_Projects_Database!$R65,"Link 1"),"") -> Link 1 | Z65: =IF(CCUS_Projects_Database!$S65<>"",HYPERLINK(CCUS_Projects_Database!$S65,"Link 2"),"") -> Link 2 | AA65: =IF(CCUS_Projects_Database!$T65<>"",HYPERLINK(CCUS_Projects_Database!$T65,"Link 3"),"") -> Link 3 | AB65: =IF(CCUS_Projects_Database!$U65<>"",HYPERLINK(CCUS_Projects_Database!$U65,"Link 4"),"") -> Link 4 | AC65: =IF(CCUS_Projects_Database!$V65<>"",HYPERLINK(CCUS_Projects_Database!$V65,"Link 5"),"") | AD65: =IF(CCUS_Projects_Database!$W65<>"",HYPERLINK(CCUS_Projects_Database!$W65,"Link 6"),"") | AE65: =IF(CCUS_Projects_Database!$X65<>"",HYPERLINK(CCUS_Projects_Database!$X65,"Link 7"),"")
A66: Athabasca Banks Carbon Hub (ALB) | B66: 496 | C66: Canada | D66: Vault 44.01 Ltd. and Moraine Initiatives Ltd. | E66: Storage | F66: 2022 | G66: 2024 | H66: 2027 | J66: Planned | N66: Storage | O66: Dedicated storage | P66: Athabasca Banks Carbon Hub (ALB) | Q66: North America | Y66: =IF(CCUS_Projects_Database!$R66<>"",HYPERLINK(CCUS_Projects_Database!$R66,"Link 1"),"") | Z66: =IF(CCUS_Projects_Database!$S66<>"",HYPERLINK(CCUS_Projects_Database!$S66,"Link 2"),"") | AA66: =IF(CCUS_Projects_Database!$T66<>"",HYPERLINK(CCUS_Projects_Database!$T66,"Link 3"),"") | AB66: =IF(CCUS_Projects_Database!$U66<>"",HYPERLINK(CCUS_Projects_Database!$U66,"Link 4"),"") | AC66: =IF(CCUS_Projects_Database!$V66<>"",HYPERLINK(CCUS_Projects_Database!$V66,"Link 5"),"") | AD66: =IF(CCUS_Projects_Database!$W66<>"",HYPERLINK(CCUS_Projects_Database!$W66,"Link 6"),"") | AE66: =IF(CCUS_Projects_Database!$X66<>"",HYPERLINK(CCUS_Projects_Database!$X66,"Link 7"),"")
A67: Athabasca Leismer project (ALB) | B67: 607 | C67: Canada | D67: Entropy Inc, Athabasca Oil Corporation | E67: Full chain | F67: 2022 | H67: 2025 | J67: Planned | L67: 0.44 | M67: 0.44 | N67: Other fuel transformation | O67: Unknown/unspecified | Q67: North America | R67: https://www.eralberta.ca/projects/details/entropy-carbon-capture-and-sequestration-of-in-situ-oil-production-process-at-athabascas-leismer-facility/ | S67: https://financialpost.com/commodities/energy/oil-gas/athabasca-oil-carbon-capture-project-oilsands | Y67: =IF(CCUS_Projects_Database!$R67<>"",HYPERLINK(CCUS_Projects_Database!$R67,"Link 1"),"") -> Link 1 | Z67: =IF(CCUS_Projects_Database!$S67<>"",HYPERLINK(CCUS_Projects_Database!$S67,"Link 2"),"") -> Link 2 | AA67: =IF(CCUS_Projects_Database!$T67<>"",HYPERLINK(CCUS_Projects_Database!$T67,"Link 3"),"") | AB67: =IF(CCUS_Projects_Database!$U67<>"",HYPERLINK(CCUS_Projects_Database!$U67,"Link 4"),"") | AC67: =IF(CCUS_Projects_Database!$V67<>"",HYPERLINK(CCUS_Projects_Database!$V67,"Link 5"),"") | AD67: =IF(CCUS_Projects_Database!$W67<>"",HYPERLINK(CCUS_Projects_Database!$W67,"Link 6"),"") | AE67: =IF(CCUS_Projects_Database!$X67<>"",HYPERLINK(CCUS_Projects_Database!$X67,"Link 7"),"")
A68: Atlantic Coast CO2 Emissions Storage Sink (ACCESS) (FL) | B68: 973 | C68: United States | D68: Southern States Energy Board | E68: Storage | F68: 2023 | J68: Planned | N68: Storage | O68: Dedicated storage | P68: Project ACCESS (FL) | Q68: North America | R68: https://www.energy.gov/fecm/project-selections-foa-2711-carbon-storage-validation-and-testing-round-2 | S68: https://omniamidstream.com/project/permian-regional-carbon-sequestration-prcs-hub | Y68: =IF(CCUS_Projects_Database!$R68<>"",HYPERLINK(CCUS_Projects_Database!$R68,"Link 1"),"") -> Link 1 | Z68: =IF(CCUS_Projects_Database!$S68<>"",HYPERLINK(CCUS_Projects_Database!$S68,"Link 2"),"") -> Link 2 | AA68: =IF(CCUS_Projects_Database!$T68<>"",HYPERLINK(CCUS_Projects_Database!$T68,"Link 3"),"") | AB68: =IF(CCUS_Projects_Database!$U68<>"",HYPERLINK(CCUS_Projects_Database!$U68,"Link 4"),"") | AC68: =IF(CCUS_Projects_Database!$V68<>"",HYPERLINK(CCUS_Projects_Database!$V68,"Link 5"),"") | AD68: =IF(CCUS_Projects_Database!$W68<>"",HYPERLINK(CCUS_Projects_Database!$W68,"Link 6"),"") | AE68: =IF(CCUS_Projects_Database!$X68<>"",HYPERLINK(CCUS_Projects_Database!$X68,"Link 7"),"")
A69: Atlas Carbon Sequestration Hub Phase 1 (Shell's Polaris Carbon Capture project Shell hub) (ALB) | B69: 39 | C69: Canada | D69: Shell Canada Limited | E69: Full chain | F69: 2021 | G69: 2024 | H69: 2025 | J69: Planned | K69: 1 | L69: 0.75 | M69: 0.75 | N69: Other fuel transformation | O69: Dedicated storage | P69: Atlas Carbon Sequestration Hub (ALB) | Q69: North America | R69: https://www.linkedin.com/pulse/alberta-selects-shell-suncor-atco-atlas-carbon-hub-proposal-/ | S69: https://www.beaver.ab.ca/public/download/files/231170 | T69: https://www.keyera.com/investors/news/keyera-and-shell-sign-agreement-to-advance-clean-energy/ | Y69: =IF(CCUS_Projects_Database!$R69<>"",HYPERLINK(CCUS_Projects_Database!$R69,"Link 1"),"") -> Link 1 | Z69: =IF(CCUS_Projects_Database!$S69<>"",HYPERLINK(CCUS_Projects_Database!$S69,"Link 2"),"") -> Link 2 | AA69: =IF(CCUS_Projects_Database!$T69<>"",HYPERLINK(CCUS_Projects_Database!$T69,"Link 3"),"") -> Link 3 | AB69: =IF(CCUS_Projects_Database!$U69<>"",HYPERLINK(CCUS_Projects_Database!$U69,"Link 4"),"") | AC69: =IF(CCUS_Projects_Database!$V69<>"",HYPERLINK(CCUS_Projects_Database!$V69,"Link 5"),"") | AD69: =IF(CCUS_Projects_Database!$W69<>"",HYPERLINK(CCUS_Projects_Database!$W69,"Link 6"),"") | AE69: =IF(CCUS_Projects_Database!$X69<>"",HYPERLINK(CCUS_Projects_Database!$X69,"Link 7"),"")
A70: Atlas Carbon Sequestration Hub Phase 2 (ALB) | B70: 40 | C70: Canada | D70: Shell Canada Limited, ATCO Energy Solutions, Suncor Energy | E70: T&S | F70: 2022 | H70: 2025 | J70: Planned | K70: 2 | L70: 9.25 | M70: 9.25 | N70: T&S | O70: Dedicated storage | P70: Atlas Carbon Sequestration Hub (ALB) | Q70: North America | R70: https://www.upstreamonline.com/energy-transition/shell-unveils-plans-for-giant-canadian-carbon-capture-and-storage-project/2-1-1039795 | S70: https://www.shell.ca/en_ca/about-us/projects-and-sites/scotford.html | T70: https://www.shell.ca/en_ca/media/news-and-media-releases/news-releases-2021/shell-proposes-large-scale-ccs-facility-in-alberta.html | U70: https://www.energyvoice.com/renewables-energy-transition/ccs/americas-ccs/336709/shell-polaris-ccs-alberta/ | V70: https://www.linkedin.com/pulse/alberta-selects-shell-suncor-atco-atlas-carbon-hub-proposal-/?trk=organization-update-content_share-article | Y70: =IF(CCUS_Projects_Database!$R70<>"",HYPERLINK(CCUS_Projects_Database!$R70,"Link 1"),"") -> Link 1 | Z70: =IF(CCUS_Projects_Database!$S70<>"",HYPERLINK(CCUS_Projects_Database!$S70,"Link 2"),"") -> Link 2 | AA70: =IF(CCUS_Projects_Database!$T70<>"",HYPERLINK(CCUS_Projects_Database!$T70,"Link 3"),"") -> Link 3 | AB70: =IF(CCUS_Projects_Database!$U70<>"",HYPERLINK(CCUS_Projects_Database!$U70,"Link 4"),"") -> Link 4 | AC70: =IF(CCUS_Projects_Database!$V70<>"",HYPERLINK(CCUS_Projects_Database!$V70,"Link 5"),"") -> Link 5 | AD70: =IF(CCUS_Projects_Database!$W70<>"",HYPERLINK(CCUS_Projects_Database!$W70,"Link 6"),"") | AE70: =IF(CCUS_Projects_Database!$X70<>"",HYPERLINK(CCUS_Projects_Database!$X70,"Link 7"),"")
A71: Augusta C2 | B71: 687 | C71: Italy-Greece | D71: Buzzi Unicem Spa | E71: Transport | F71: 2022 | H71: 2029 | J71: Planned | L71: 0.2 | M71: 0.2 | N71: Transport | O71: Dedicated storage | P71: Augusta-C2/Prinos CO2 storage | Q71: Europe | R71: https://zeroemissionsplatform.eu/wp-content/uploads/Detailed_information_regarding_the_candidate_projects_CO2_networks_Dec_2022_v2.pdf | Y71: =IF(CCUS_Projects_Database!$R71<>"",HYPERLINK(CCUS_Projects_Database!$R71,"Link 1"),"") -> Link 1 | Z71: =IF(CCUS_Projects_Database!$S71<>"",HYPERLINK(CCUS_Projects_Database!$S71,"Link 2"),"") | AA71: =IF(CCUS_Projects_Database!$T71<>"",HYPERLINK(CCUS_Projects_Database!$T71,"Link 3"),"") | AB71: =IF(CCUS_Projects_Database!$U71<>"",HYPERLINK(CCUS_Projects_Database!$U71,"Link 4"),"") | AC71: =IF(CCUS_Projects_Database!$V71<>"",HYPERLINK(CCUS_Projects_Database!$V71,"Link 5"),"") | AD71: =IF(CCUS_Projects_Database!$W71<>"",HYPERLINK(CCUS_Projects_Database!$W71,"Link 6"),"") | AE71: =IF(CCUS_Projects_Database!$X71<>"",HYPERLINK(CCUS_Projects_Database!$X71,"Link 7"),"")
A72: Aukra Hydrogen Hub | B72: 41 | C72: Norway | D72: Aker Horizons, Shell, CapeOmega | E72: Full chain | F72: 2021 | G72: 2024 | H72: 2030 | J72: Planned | N72: Hydrogen or ammonia | O72: Unknown/unspecified | Q72: Europe | R72: https://news.cision.com/aker-clean-hydrogen/r/aker-clean-hydrogen-to-explore-hydrogen-production-facility-opportunities-in-aukra-in-norway,c3382436 | S72: https://akerhorizons.com/what-we-do/aukra/ | Y72: =IF(CCUS_Projects_Database!$R72<>"",HYPERLINK(CCUS_Projects_Database!$R72,"Link 1"),"") -> Link 1 | Z72: =IF(CCUS_Projects_Database!$S72<>"",HYPERLINK(CCUS_Projects_Database!$S72,"Link 2"),"") -> Link 2 | AA72: =IF(CCUS_Projects_Database!$T72<>"",HYPERLINK(CCUS_Projects_Database!$T72,"Link 3"),"") | AB72: =IF(CCUS_Projects_Database!$U72<>"",HYPERLINK(CCUS_Projects_Database!$U72,"Link 4"),"") | AC72: =IF(CCUS_Projects_Database!$V72<>"",HYPERLINK(CCUS_Projects_Database!$V72,"Link 5"),"") | AD72: =IF(CCUS_Projects_Database!$W72<>"",HYPERLINK(CCUS_Projects_Database!$W72,"Link 6"),"") | AE72: =IF(CCUS_Projects_Database!$X72<>"",HYPERLINK(CCUS_Projects_Database!$X72,"Link 7"),"")
A73: Avedøre Power Station CCS | B73: 42 | C73: Denmark | D73: Orsted, Aker CC (tech) | E73: Capture | F73: 2021 | G73: 2023 | H73: 2026 | J73: Under construction | K73: 1 | L73: 0.15 | M73: 0.15 | N73: Power and heat | O73: Dedicated storage | P73: Northern Lights | Q73: Europe | R73: https://orsted.com/en/media/newsroom/news/2021/06/857452362384936 | S73: https://orsted.com/en/media/newsroom/news/2022/06/20220613532911 | T73: https://orsted.com/en/media/newsroom/news/2022/06/20220613532911 | U73: https://akercarboncapture.com/?cision_id=E626D6BD3CFDB96F | V73: https://orsted.com/en/media/newsroom/news/2023/12/oersted-begins-construction-of-denmarks-first-carb-13757543 | Y73: =IF(CCUS_Projects_Database!$R73<>"",HYPERLINK(CCUS_Projects_Database!$R73,"Link 1"),"") -> Link 1 | Z73: =IF(CCUS_Projects_Database!$S73<>"",HYPERLINK(CCUS_Projects_Database!$S73,"Link 2"),"") -> Link 2 | AA73: =IF(CCUS_Projects_Database!$T73<>"",HYPERLINK(CCUS_Projects_Database!$T73,"Link 3"),"") -> Link 3 | AB73: =IF(CCUS_Projects_Database!$U73<>"",HYPERLINK(CCUS_Projects_Database!$U73,"Link 4"),"") -> Link 4 | AC73: =IF(CCUS_Projects_Database!$V73<>"",HYPERLINK(CCUS_Projects_Database!$V73,"Link 5"),"") -> Link 5 | AD73: =IF(CCUS_Projects_Database!$W73<>"",HYPERLINK(CCUS_Projects_Database!$W73,"Link 6"),"") | AE73: =IF(CCUS_Projects_Database!$X73<>"",HYPERLINK(CCUS_Projects_Database!$X73,"Link 7"),"")
A74: Avedøre Power Station CCU (Green Fuels for Denmark) | B74: 757 | C74: Denmark | D74: Orsted | E74: CCU | F74: 2021 | H74: 2026 | J74: Planned | K74: 2 | N74: Power and heat | O74: Use | Q74: Europe | R74: https://orsted.com/en/media/newsroom/news/2022/12/13666863 | S74: https://orsted.com/en/media/newsroom/news/2021/06/857452362384936 | Y74: =IF(CCUS_Projects_Database!$R74<>"",HYPERLINK(CCUS_Projects_Database!$R74,"Link 1"),"") -> Link 1 | Z74: =IF(CCUS_Projects_Database!$S74<>"",HYPERLINK(CCUS_Projects_Database!$S74,"Link 2"),"") -> Link 2 | AA74: =IF(CCUS_Projects_Database!$T74<>"",HYPERLINK(CCUS_Projects_Database!$T74,"Link 3"),"") | AB74: =IF(CCUS_Projects_Database!$U74<>"",HYPERLINK(CCUS_Projects_Database!$U74,"Link 4"),"") | AC74: =IF(CCUS_Projects_Database!$V74<>"",HYPERLINK(CCUS_Projects_Database!$V74,"Link 5"),"") | AD74: =IF(CCUS_Projects_Database!$W74<>"",HYPERLINK(CCUS_Projects_Database!$W74,"Link 6"),"") | AE74: =IF(CCUS_Projects_Database!$X74<>"",HYPERLINK(CCUS_Projects_Database!$X74,"Link 7"),"")
A75: Babcock & Wilcox’s (LA) | B75: 830 | C75: United States | D75: Babcock & Wilcox’s, CGI Gases (CO2 offtaker, transport), General Hydrogen (H2 offtaker) | E75: Capture | F75: 2023 | H75: 2026 | J75: Planned | N75: Hydrogen or ammonia | O75: Unknown/unspecified | Q75: North America | R75: https://www.power-eng.com/hydrogen/hydrogen-co2-to-be-produced-at-babcock-wilcox-biomass-fueled-plant/#gref | Y75: =IF(CCUS_Projects_Database!$R75<>"",HYPERLINK(CCUS_Projects_Database!$R75,"Link 1"),"") -> Link 1 | Z75: =IF(CCUS_Projects_Database!$S75<>"",HYPERLINK(CCUS_Projects_Database!$S75,"Link 2"),"") | AA75: =IF(CCUS_Projects_Database!$T75<>"",HYPERLINK(CCUS_Projects_Database!$T75,"Link 3"),"") | AB75: =IF(CCUS_Projects_Database!$U75<>"",HYPERLINK(CCUS_Projects_Database!$U75,"Link 4"),"") | AC75: =IF(CCUS_Projects_Database!$V75<>"",HYPERLINK(CCUS_Projects_Database!$V75,"Link 5"),"") | AD75: =IF(CCUS_Projects_Database!$W75<>"",HYPERLINK(CCUS_Projects_Database!$W75,"Link 6"),"") | AE75: =IF(CCUS_Projects_Database!$X75<>"",HYPERLINK(CCUS_Projects_Database!$X75,"Link 7"),"")
A76: Bacton Thames Net Zero | B76: 519 | C76: United Kingdom | D76: Eni | E76: T&S | F76: 2022 | G76: 2027 | H76: 2030 | J76: Planned | L76: 7.5 | M76: 10 | N76: T&S | O76: Dedicated storage | P76: Bacton Thames Net Zero initiative | Q76: Europe | R76: https://www.eni.com/en-IT/media/press-release/2022/09/eni-uk-applies-for-carbon-storage-license-for-hewett-depleted-field.html | S76: https://www.eni.com/static/bactonthamesnetzero/ | T76: https://www.corygroup.co.uk/media/news-insights/cory-supports-launch-bacton-thames-net-zero-cooperation-agreement/ | U76: https://enfinium.co.uk/enfinium-joins-the-bacton-thames-net-zero-cooperation-agreement/ | Y76: =IF(CCUS_Projects_Database!$R76<>"",HYPERLINK(CCUS_Projects_Database!$R76,"Link 1"),"") -> Link 1 | Z76: =IF(CCUS_Projects_Database!$S76<>"",HYPERLINK(CCUS_Projects_Database!$S76,"Link 2"),"") -> Link 2 | AA76: =IF(CCUS_Projects_Database!$T76<>"",HYPERLINK(CCUS_Projects_Database!$T76,"Link 3"),"") -> Link 3 | AB76: =IF(CCUS_Projects_Database!$U76<>"",HYPERLINK(CCUS_Projects_Database!$U76,"Link 4"),"") -> Link 4 | AC76: =IF(CCUS_Projects_Database!$V76<>"",HYPERLINK(CCUS_Projects_Database!$V76,"Link 5"),"") | AD76: =IF(CCUS_Projects_Database!$W76<>"",HYPERLINK(CCUS_Projects_Database!$W76,"Link 6"),"") | AE76: =IF(CCUS_Projects_Database!$X76<>"",HYPERLINK(CCUS_Projects_Database!$X76,"Link 7"),"")
A77: Balikpapan Refinery | B77: 43 | C77: Indonesia | D77: Pertamina, Air Liquide | E77: Full chain | F77: 2022 | H77: 2030 | J77: Planned | L77: 1.4 | M77: 1.4 | N77: Other fuel transformation | O77: Mixed | P77: Kutai Basin CCUS hub | Q77: Other Asia Pacific | R77: https://www.pertamina.com/en/news-room/news-release/pertamina-air-liquide-agree-to-collaborate-in-developing-ccu-technology-at-the-balikpapan-refinery | S77: https://acnf.jp/program/file/presentation/7_Panelist_MEMR-IDN.pdf | Y77: =IF(CCUS_Projects_Database!$R77<>"",HYPERLINK(CCUS_Projects_Database!$R77,"Link 1"),"") -> Link 1 | Z77: =IF(CCUS_Projects_Database!$S77<>"",HYPERLINK(CCUS_Projects_Database!$S77,"Link 2"),"") -> Link 2 | AA77: =IF(CCUS_Projects_Database!$T77<>"",HYPERLINK(CCUS_Projects_Database!$T77,"Link 3"),"") | AB77: =IF(CCUS_Projects_Database!$U77<>"",HYPERLINK(CCUS_Projects_Database!$U77,"Link 4"),"") | AC77: =IF(CCUS_Projects_Database!$V77<>"",HYPERLINK(CCUS_Projects_Database!$V77,"Link 5"),"") | AD77: =IF(CCUS_Projects_Database!$W77<>"",HYPERLINK(CCUS_Projects_Database!$W77,"Link 6"),"") | AE77: =IF(CCUS_Projects_Database!$X77<>"",HYPERLINK(CCUS_Projects_Database!$X77,"Link 7"),"")
A78: Banggai ammonia plant Central Sulawesi | B78: 342 | C78: Indonesia | D78: JOGMEC, Mitsubishi, PT Panca Amara Utama, ITB, Pertamina | E78: Full chain | F78: 2021 | J78: Planned | N78: Hydrogen or ammonia | O78: Unknown/unspecified | Q78: Other Asia Pacific | R78: https://www.mitsubishicorp.com/jp/en/pr/archive/2021/html/0000046720.html | S78: https://acnf.jp/program/file/presentation/7_Panelist_MEMR-IDN.pdf | Y78: =IF(CCUS_Projects_Database!$R78<>"",HYPERLINK(CCUS_Projects_Database!$R78,"Link 1"),"") -> Link 1 | Z78: =IF(CCUS_Projects_Database!$S78<>"",HYPERLINK(CCUS_Projects_Database!$S78,"Link 2"),"") -> Link 2 | AA78: =IF(CCUS_Projects_Database!$T78<>"",HYPERLINK(CCUS_Projects_Database!$T78,"Link 3"),"") | AB78: =IF(CCUS_Projects_Database!$U78<>"",HYPERLINK(CCUS_Projects_Database!$U78,"Link 4"),"") | AC78: =IF(CCUS_Projects_Database!$V78<>"",HYPERLINK(CCUS_Projects_Database!$V78,"Link 5"),"") | AD78: =IF(CCUS_Projects_Database!$W78<>"",HYPERLINK(CCUS_Projects_Database!$W78,"Link 6"),"") | AE78: =IF(CCUS_Projects_Database!$X78<>"",HYPERLINK(CCUS_Projects_Database!$X78,"Link 7"),"")
A79: Baotou Steel (Inner Mongolia) phase 1 | B79: 1053 | C79: People's Republic of China | D79: Baotou Steel Group | E79: Full Chain | F79: 2022 | G79: 2022 | H79: 2026 | J79: Under construction | K79: 1 | L79: 0.5 | M79: 0.5 | N79: Iron and steel | O79: Unknown/unspecified | Q79: Other Asia Pacific | R79: https://group.pingan.com/media/news/2023/pingan-bank-grants-first-loan-to-pioneering-CCUS-project.html | S79: https://www.scmp.com/business/article/3225578/climate-finance-chinas-ping-bank-lends-us25-million-inner-mongolia-steel-maker-capture-carbon | Y79: =IF(CCUS_Projects_Database!$R79<>"",HYPERLINK(CCUS_Projects_Database!$R79,"Link 1"),"") -> Link 1 | Z79: =IF(CCUS_Projects_Database!$S79<>"",HYPERLINK(CCUS_Projects_Database!$S79,"Link 2"),"") -> Link 2 | AA79: =IF(CCUS_Projects_Database!$T79<>"",HYPERLINK(CCUS_Projects_Database!$T79,"Link 3"),"") | AB79: =IF(CCUS_Projects_Database!$U79<>"",HYPERLINK(CCUS_Projects_Database!$U79,"Link 4"),"") | AC79: =IF(CCUS_Projects_Database!$V79<>"",HYPERLINK(CCUS_Projects_Database!$V79,"Link 5"),"") | AD79: =IF(CCUS_Projects_Database!$W79<>"",HYPERLINK(CCUS_Projects_Database!$W79,"Link 6"),"") | AE79: =IF(CCUS_Projects_Database!$X79<>"",HYPERLINK(CCUS_Projects_Database!$X79,"Link 7"),"")
A80: Baotou Steel (Inner Mongolia) phase 2 | B80: 1054 | C80: People's Republic of China | D80: Baotou Steel Group | E80: Full Chain | F80: 2022 | G80: 2022 | H80: 2027 | J80: Under construction | K80: 2 | L80: 1.5 | M80: 1.5 | N80: Iron and steel | O80: Unknown/unspecified | Q80: Other Asia Pacific | R80: https://group.pingan.com/media/news/2023/pingan-bank-grants-first-loan-to-pioneering-CCUS-project.html | S80: https://www.scmp.com/business/article/3225578/climate-finance-chinas-ping-bank-lends-us25-million-inner-mongolia-steel-maker-capture-carbon | Y80: =IF(CCUS_Projects_Database!$R80<>"",HYPERLINK(CCUS_Projects_Database!$R80,"Link 1"),"") -> Link 1 | Z80: =IF(CCUS_Projects_Database!$S80<>"",HYPERLINK(CCUS_Projects_Database!$S80,"Link 2"),"") -> Link 2 | AA80: =IF(CCUS_Projects_Database!$T80<>"",HYPERLINK(CCUS_Projects_Database!$T80,"Link 3"),"") | AB80: =IF(CCUS_Projects_Database!$U80<>"",HYPERLINK(CCUS_Projects_Database!$U80,"Link 4"),"") | AC80: =IF(CCUS_Projects_Database!$V80<>"",HYPERLINK(CCUS_Projects_Database!$V80,"Link 5"),"") | AD80: =IF(CCUS_Projects_Database!$W80<>"",HYPERLINK(CCUS_Projects_Database!$W80,"Link 6"),"") | AE80: =IF(CCUS_Projects_Database!$X80<>"",HYPERLINK(CCUS_Projects_Database!$X80,"Link 7"),"")
A81: Bapco MOL CCUS value chain | B81: 949 | C81: Bahrain | D81: Bapco energies (storage), MOL (transport) | E81: T&S | F81: 2023 | J81: Planned | N81: T&S | O81: Dedicated storage | Q81: Middle East | R81: https://www.mol.co.jp/en/pr/2023/23147.html | Y81: =IF(CCUS_Projects_Database!$R81<>"",HYPERLINK(CCUS_Projects_Database!$R81,"Link 1"),"") -> Link 1 | Z81: =IF(CCUS_Projects_Database!$S81<>"",HYPERLINK(CCUS_Projects_Database!$S81,"Link 2"),"") | AA81: =IF(CCUS_Projects_Database!$T81<>"",HYPERLINK(CCUS_Projects_Database!$T81,"Link 3"),"") | AB81: =IF(CCUS_Projects_Database!$U81<>"",HYPERLINK(CCUS_Projects_Database!$U81,"Link 4"),"") | AC81: =IF(CCUS_Projects_Database!$V81<>"",HYPERLINK(CCUS_Projects_Database!$V81,"Link 5"),"") | AD81: =IF(CCUS_Projects_Database!$W81<>"",HYPERLINK(CCUS_Projects_Database!$W81,"Link 6"),"") | AE81: =IF(CCUS_Projects_Database!$X81<>"",HYPERLINK(CCUS_Projects_Database!$X81,"Link 7"),"")
A82: Barents Blue ammonia project Train 1 | B82: 44 | C82: Norway | D82: Horisont Energi (50%), Fertiberia (50%) | E82: Capture | F82: 2021 | G82: 2024 | H82: 2028 | J82: Planned | K82: 1 | L82: 1.92 | M82: 2 | N82: Hydrogen or ammonia | O82: Dedicated storage | P82: Polaris offshore storage facility (Errai project) | Q82: Europe | R82: https://www.ammoniaenergy.org/articles/barents-blue-ammonia-plant-gains-new-partners-set-to-triple-in-size/ | S82: https://www.horisontenergi.no/esa-approves-state-aid-for-barents-blue-project/ | Y82: =IF(CCUS_Projects_Database!$R82<>"",HYPERLINK(CCUS_Projects_Database!$R82,"Link 1"),"") -> Link 1 | Z82: =IF(CCUS_Projects_Database!$S82<>"",HYPERLINK(CCUS_Projects_Database!$S82,"Link 2"),"") -> Link 2 | AA82: =IF(CCUS_Projects_Database!$T82<>"",HYPERLINK(CCUS_Projects_Database!$T82,"Link 3"),"") | AB82: =IF(CCUS_Projects_Database!$U82<>"",HYPERLINK(CCUS_Projects_Database!$U82,"Link 4"),"") | AC82: =IF(CCUS_Projects_Database!$V82<>"",HYPERLINK(CCUS_Projects_Database!$V82,"Link 5"),"") | AD82: =IF(CCUS_Projects_Database!$W82<>"",HYPERLINK(CCUS_Projects_Database!$W82,"Link 6"),"") | AE82: =IF(CCUS_Projects_Database!$X82<>"",HYPERLINK(CCUS_Projects_Database!$X82,"Link 7"),"")
A83: Barents Blue ammonia project Train 2 | B83: 45 | C83: Norway | D83: Horisont Energi (50%), Fertiberia (50%) | E83: Capture | F83: 2021 | J83: Planned | K83: 2 | L83: 1.92 | M83: 2 | N83: Hydrogen or ammonia | O83: Dedicated storage | P83: Polaris offshore storage facility (Errai project) | Q83: Europe | R83: https://www.ammoniaenergy.org/articles/barents-blue-ammonia-plant-gains-new-partners-set-to-triple-in-size/ | S83: https://www.horisontenergi.no/esa-approves-state-aid-for-barents-blue-project/ | Y83: =IF(CCUS_Projects_Database!$R83<>"",HYPERLINK(CCUS_Projects_Database!$R83,"Link 1"),"") -> Link 1 | Z83: =IF(CCUS_Projects_Database!$S83<>"",HYPERLINK(CCUS_Projects_Database!$S83,"Link 2"),"") -> Link 2 | AA83: =IF(CCUS_Projects_Database!$T83<>"",HYPERLINK(CCUS_Projects_Database!$T83,"Link 3"),"") | AB83: =IF(CCUS_Projects_Database!$U83<>"",HYPERLINK(CCUS_Projects_Database!$U83,"Link 4"),"") | AC83: =IF(CCUS_Projects_Database!$V83<>"",HYPERLINK(CCUS_Projects_Database!$V83,"Link 5"),"") | AD83: =IF(CCUS_Projects_Database!$W83<>"",HYPERLINK(CCUS_Projects_Database!$W83,"Link 6"),"") | AE83: =IF(CCUS_Projects_Database!$X83<>"",HYPERLINK(CCUS_Projects_Database!$X83,"Link 7"),"")
A84: Barents Blue ammonia project Train 3 | B84: 46 | C84: Norway | D84: Horisont Energi (50%), Fertiberia (50%) | E84: Capture | F84: 2021 | J84: Planned | K84: 3 | L84: 1.92 | M84: 2 | N84: Hydrogen or ammonia | O84: Dedicated storage | P84: Polaris offshore storage facility (Errai project) | Q84: Europe | R84: https://www.ammoniaenergy.org/articles/barents-blue-ammonia-plant-gains-new-partners-set-to-triple-in-size/ | S84: https://www.horisontenergi.no/esa-approves-state-aid-for-barents-blue-project/ | Y84: =IF(CCUS_Projects_Database!$R84<>"",HYPERLINK(CCUS_Projects_Database!$R84,"Link 1"),"") -> Link 1 | Z84: =IF(CCUS_Projects_Database!$S84<>"",HYPERLINK(CCUS_Projects_Database!$S84,"Link 2"),"") -> Link 2 | AA84: =IF(CCUS_Projects_Database!$T84<>"",HYPERLINK(CCUS_Projects_Database!$T84,"Link 3"),"") | AB84: =IF(CCUS_Projects_Database!$U84<>"",HYPERLINK(CCUS_Projects_Database!$U84,"Link 4"),"") | AC84: =IF(CCUS_Projects_Database!$V84<>"",HYPERLINK(CCUS_Projects_Database!$V84,"Link 5"),"") | AD84: =IF(CCUS_Projects_Database!$W84<>"",HYPERLINK(CCUS_Projects_Database!$W84,"Link 6"),"") | AE84: =IF(CCUS_Projects_Database!$X84<>"",HYPERLINK(CCUS_Projects_Database!$X84,"Link 7"),"")
A85: Barossa and Darwin liquefied natural gas (DLNG) CCUS | B85: 47 | C85: Australia | D85: Santos (43.4%), SK E&S, JERA | E85: Capture | F85: 2021 | G85: 2024 | H85: 2025 | J85: Planned | L85: 2.3 | M85: 2.3 | N85: Natural gas processing/LNG | O85: Dedicated storage | P85: Bayu-Undan field storage hub | Q85: Australia and New Zealand | R85: https://www.upstreamonline.com/energy-transition/santos-betting-big-on-carbon-capture-in-bid-to-drive-down-emissions/2-1-1053585 | S85: https://www.oedigital.com/news/491510-santos-could-store-co2-from-barossa-field-in-depleted-bayu-undan-reservoir | T85: https://www.santos.com/news/globally-significant-carbon-capture-and-storage-project-a-step-closer/ | U85: https://www.energyvoice.com/renewables-energy-transition/393749/santos-enters-feed-for-giant-ccs-project-at-bayu-undan-offshore-east-timor/ | V85: https://www.spglobal.com/commodityinsights/en/ci/research-analysis/santos-darwin-pipeline-duplication-dpd-project-confirmed-au.html | W85: https://www.prnewswire.com/apac/news-releases/honeywell-to-collaborate-with-sk-es-to-deploy-carbon-capture-technology-across-korea-and-southeast-asia-301941319.html | Y85: =IF(CCUS_Projects_Database!$R85<>"",HYPERLINK(CCUS_Projects_Database!$R85,"Link 1"),"") -> Link 1 | Z85: =IF(CCUS_Projects_Database!$S85<>"",HYPERLINK(CCUS_Projects_Database!$S85,"Link 2"),"") -> Link 2 | AA85: =IF(CCUS_Projects_Database!$T85<>"",HYPERLINK(CCUS_Projects_Database!$T85,"Link 3"),"") -> Link 3 | AB85: =IF(CCUS_Projects_Database!$U85<>"",HYPERLINK(CCUS_Projects_Database!$U85,"Link 4"),"") -> Link 4 | AC85: =IF(CCUS_Projects_Database!$V85<>"",HYPERLINK(CCUS_Projects_Database!$V85,"Link 5"),"") -> Link 5 | AD85: =IF(CCUS_Projects_Database!$W85<>"",HYPERLINK(CCUS_Projects_Database!$W85,"Link 6"),"") -> Link 6 | AE85: =IF(CCUS_Projects_Database!$X85<>"",HYPERLINK(CCUS_Projects_Database!$X85,"Link 7"),"")
A86: Battle River Carbon Hub (ALB) | B86: 497 | C86: Canada | D86: Heartland Generation Ltd., Carbon Alpha | E86: Storage | F86: 2022 | G86: 2024 | H86: 2027 | J86: Planned | L86: 5 | M86: 5 | N86: Storage | O86: Dedicated storage | P86: Battle River Carbon Hub (ALB) | Q86: North America | R86: https://www.alberta.ca/carbon-capture-utilization-and-storage-hub-development-process.aspx | S86: https://www.linkedin.com/posts/carbon-alpha_heartland-generation-battle-river-carbon-activity-6973270756914851840-aiw8/?trk=public_profile_like_view&originalSubdomain=ca | T86: https://www.heartlandgeneration.com/post/heartland-generation-selected-by-government-of-alberta-to-evaluate-a-carbon-sequestration-hub-in-alberta | Y86: =IF(CCUS_Projects_Database!$R86<>"",HYPERLINK(CCUS_Projects_Database!$R86,"Link 1"),"") -> Link 1 | Z86: =IF(CCUS_Projects_Database!$S86<>"",HYPERLINK(CCUS_Projects_Database!$S86,"Link 2"),"") -> Link 2 | AA86: =IF(CCUS_Projects_Database!$T86<>"",HYPERLINK(CCUS_Projects_Database!$T86,"Link 3"),"") -> Link 3 | AB86: =IF(CCUS_Projects_Database!$U86<>"",HYPERLINK(CCUS_Projects_Database!$U86,"Link 4"),"") | AC86: =IF(CCUS_Projects_Database!$V86<>"",HYPERLINK(CCUS_Projects_Database!$V86,"Link 5"),"") | AD86: =IF(CCUS_Projects_Database!$W86<>"",HYPERLINK(CCUS_Projects_Database!$W86,"Link 6"),"") | AE86: =IF(CCUS_Projects_Database!$X86<>"",HYPERLINK(CCUS_Projects_Database!$X86,"Link 7"),"")
A87: Bayou Bend CCS offshore (TX) | B87: 49 | C87: United States | D87: Chevron (50%), Talos Energy (25% and operator), Equinor (25%) | E87: Storage | F87: 2021 | J87: Planned | N87: Storage | O87: Dedicated storage | P87: Bayou Bend CCS offshore (TX) | Q87: North America | R87: https://www.talosenergy.com/operations/carbon-capture-and-sequestration/default.aspx | S87: https://www.offshore-mag.com/energy-transition/article/14298218/equinor-joins-chevron-talos-on-bayou-bend-ccs-project | Y87: =IF(CCUS_Projects_Database!$R87<>"",HYPERLINK(CCUS_Projects_Database!$R87,"Link 1"),"") -> Link 1 | Z87: =IF(CCUS_Projects_Database!$S87<>"",HYPERLINK(CCUS_Projects_Database!$S87,"Link 2"),"") -> Link 2 | AA87: =IF(CCUS_Projects_Database!$T87<>"",HYPERLINK(CCUS_Projects_Database!$T87,"Link 3"),"") | AB87: =IF(CCUS_Projects_Database!$U87<>"",HYPERLINK(CCUS_Projects_Database!$U87,"Link 4"),"") | AC87: =IF(CCUS_Projects_Database!$V87<>"",HYPERLINK(CCUS_Projects_Database!$V87,"Link 5"),"") | AD87: =IF(CCUS_Projects_Database!$W87<>"",HYPERLINK(CCUS_Projects_Database!$W87,"Link 6"),"") | AE87: =IF(CCUS_Projects_Database!$X87<>"",HYPERLINK(CCUS_Projects_Database!$X87,"Link 7"),"")
A88: Bayu-Undan field storage hub Timor-Leste phase 1 | B88: 50 | C88: Australia | D88: Santos (43.4%) , SK E&S (25%), INPEX (11.4%), ENI (11%), JERA (6.1%), Tokyo Gas (3.1%) | E88: T&S | F88: 2021 | G88: 2025 | H88: 2028 | J88: Planned | K88: 1 | L88: 2.3 | M88: 2.3 | N88: T&S | O88: Dedicated storage | P88: Bayu-Undan field storage hub | Q88: Australia and New Zealand | R88: https://www.santos.com/news/globally-significant-carbon-capture-and-storage-project-a-step-closer/ | S88: https://www.spglobal.com/commodityinsights/en/ci/research-analysis/santos-darwin-pipeline-duplication-dpd-project-confirmed-au.html | T88: https://www.santos.com/wp-content/uploads/2022/03/Santos-2022-Climate-Change-Report_web.pdf | U88: https://www.santos.com/news/mous-executed-for-potential-co2-supply-to-underpin-santos-bayu-undan-ccs-project/ | V88: https://www.santos.com/news/bayu-undan-joint-venture-and-timor-gap-sign-mou-to-cooperate-on-carbon-capture-and-storage/ | Y88: =IF(CCUS_Projects_Database!$R88<>"",HYPERLINK(CCUS_Projects_Database!$R88,"Link 1"),"") -> Link 1 | Z88: =IF(CCUS_Projects_Database!$S88<>"",HYPERLINK(CCUS_Projects_Database!$S88,"Link 2"),"") -> Link 2 | AA88: =IF(CCUS_Projects_Database!$T88<>"",HYPERLINK(CCUS_Projects_Database!$T88,"Link 3"),"") -> Link 3 | AB88: =IF(CCUS_Projects_Database!$U88<>"",HYPERLINK(CCUS_Projects_Database!$U88,"Link 4"),"") -> Link 4 | AC88: =IF(CCUS_Projects_Database!$V88<>"",HYPERLINK(CCUS_Projects_Database!$V88,"Link 5"),"") -> Link 5 | AD88: =IF(CCUS_Projects_Database!$W88<>"",HYPERLINK(CCUS_Projects_Database!$W88,"Link 6"),"") | AE88: =IF(CCUS_Projects_Database!$X88<>"",HYPERLINK(CCUS_Projects_Database!$X88,"Link 7"),"")
A89: Bayu-Undan field storage hub Timor-Leste phase 2 | B89: 628 | C89: Australia | D89: Santos (43.4%) , SK E&S (25%), INPEX (11.4%), ENI (11%), JERA (6.1%), Tokyo Gas (3.1%) | E89: T&S | F89: 2021 | G89: 2025 | J89: Planned | K89: 2 | L89: 10 | M89: 10 | N89: T&S | O89: Dedicated storage | P89: Bayu-Undan field storage hub | Q89: Australia and New Zealand | R89: https://www.santos.com/wp-content/uploads/2022/03/Santos-2022-Climate-Change-Report_web.pdf | S89: https://www.santos.com/news/mous-executed-for-potential-co2-supply-to-underpin-santos-bayu-undan-ccs-project/ | Y89: =IF(CCUS_Projects_Database!$R89<>"",HYPERLINK(CCUS_Projects_Database!$R89,"Link 1"),"") -> Link 1 | Z89: =IF(CCUS_Projects_Database!$S89<>"",HYPERLINK(CCUS_Projects_Database!$S89,"Link 2"),"") -> Link 2 | AA89: =IF(CCUS_Projects_Database!$T89<>"",HYPERLINK(CCUS_Projects_Database!$T89,"Link 3"),"") | AB89: =IF(CCUS_Projects_Database!$U89<>"",HYPERLINK(CCUS_Projects_Database!$U89,"Link 4"),"") | AC89: =IF(CCUS_Projects_Database!$V89<>"",HYPERLINK(CCUS_Projects_Database!$V89,"Link 5"),"") | AD89: =IF(CCUS_Projects_Database!$W89<>"",HYPERLINK(CCUS_Projects_Database!$W89,"Link 6"),"") | AE89: =IF(CCUS_Projects_Database!$X89<>"",HYPERLINK(CCUS_Projects_Database!$X89,"Link 7"),"")
A90: Bell Bay Powerfuels project (TAS) | B90: 1044 | C90: Australia | D90: ABEL Energy, Iberdrola Australia, Johnson Matthey (methanol synthesis), Sungas Renewables (biomass gasifier) | E90: CCU | F90: 2020 | H90: 2027 | J90: Planned | M90: 0.411 | N90: Power and heat | O90: Use | Q90: Australia and New Zealand | R90: https://research.csiro.au/hyresource/abel-energy-bell-bay-powerfuels-project/ | Y90: =IF(CCUS_Projects_Database!$R90<>"",HYPERLINK(CCUS_Projects_Database!$R90,"Link 1"),"") -> Link 1 | Z90: =IF(CCUS_Projects_Database!$S90<>"",HYPERLINK(CCUS_Projects_Database!$S90,"Link 2"),"") | AA90: =IF(CCUS_Projects_Database!$T90<>"",HYPERLINK(CCUS_Projects_Database!$T90,"Link 3"),"") | AB90: =IF(CCUS_Projects_Database!$U90<>"",HYPERLINK(CCUS_Projects_Database!$U90,"Link 4"),"") | AC90: =IF(CCUS_Projects_Database!$V90<>"",HYPERLINK(CCUS_Projects_Database!$V90,"Link 5"),"") | AD90: =IF(CCUS_Projects_Database!$W90<>"",HYPERLINK(CCUS_Projects_Database!$W90,"Link 6"),"") | AE90: =IF(CCUS_Projects_Database!$X90<>"",HYPERLINK(CCUS_Projects_Database!$X90,"Link 7"),"")
A91: Beremend cement factory | B91: 1142 | C91: Hungary | D91: DDC | E91: Capture | F91: 2023 | H91: 2032 | J91: Planned | L91: 0.315 | M91: 0.315 | N91: Cement | O91: Dedicated storage | Q91: Europe | R91: https://zeroemissionsplatform.eu/wp-content/uploads/Detailed_information_regarding_the_candidate_projects_CO2_networks_Dec_2022_v2.pdf | S91: https://total-croatia-news.com/news/business/croatian-nexe/ | Y91: =IF(CCUS_Projects_Database!$R91<>"",HYPERLINK(CCUS_Projects_Database!$R91,"Link 1"),"") -> Link 1 | Z91: =IF(CCUS_Projects_Database!$S91<>"",HYPERLINK(CCUS_Projects_Database!$S91,"Link 2"),"") -> Link 2 | AA91: =IF(CCUS_Projects_Database!$T91<>"",HYPERLINK(CCUS_Projects_Database!$T91,"Link 3"),"") | AB91: =IF(CCUS_Projects_Database!$U91<>"",HYPERLINK(CCUS_Projects_Database!$U91,"Link 4"),"") | AC91: =IF(CCUS_Projects_Database!$V91<>"",HYPERLINK(CCUS_Projects_Database!$V91,"Link 5"),"") | AD91: =IF(CCUS_Projects_Database!$W91<>"",HYPERLINK(CCUS_Projects_Database!$W91,"Link 6"),"") | AE91: =IF(CCUS_Projects_Database!$X91<>"",HYPERLINK(CCUS_Projects_Database!$X91,"Link 7"),"")
A92: Berrima cement plant (NSW) | B92: 54 | C92: Australia | D92: Boral, Calix | E92: CCU | F92: 2022 | J92: Planned | L92: 0.1 | M92: 0.1 | N92: Cement | O92: Use | Q92: Australia and New Zealand | R92: https://calix.global/co2-mitigation-focus-area/calix-and-boral-to-develop-carbon-abatement-project/ | S92: https://www.leilac.com/project-boral/ | Y92: =IF(CCUS_Projects_Database!$R92<>"",HYPERLINK(CCUS_Projects_Database!$R92,"Link 1"),"") -> Link 1 | Z92: =IF(CCUS_Projects_Database!$S92<>"",HYPERLINK(CCUS_Projects_Database!$S92,"Link 2"),"") -> Link 2 | AA92: =IF(CCUS_Projects_Database!$T92<>"",HYPERLINK(CCUS_Projects_Database!$T92,"Link 3"),"") | AB92: =IF(CCUS_Projects_Database!$U92<>"",HYPERLINK(CCUS_Projects_Database!$U92,"Link 4"),"") | AC92: =IF(CCUS_Projects_Database!$V92<>"",HYPERLINK(CCUS_Projects_Database!$V92,"Link 5"),"") | AD92: =IF(CCUS_Projects_Database!$W92<>"",HYPERLINK(CCUS_Projects_Database!$W92,"Link 6"),"") | AE92: =IF(CCUS_Projects_Database!$X92<>"",HYPERLINK(CCUS_Projects_Database!$X92,"Link 7"),"")
A93: Big spring refinery (TX) pilot | B93: 1072 | C93: United States | D93: Delek, Svante | E93: Capture | F93: 2024 | H93: 2028 | J93: Planned | L93: 0.145 | M93: 0.145 | N93: Other fuel transformation | O93: Unknown/unspecified | Q93: North America | R93: https://www.energy.gov/oced/articles/oced-selects-four-projects-ky-ms-tx-and-wy-advance-technologies-reduce-harmful-carbon | S93: https://www.svanteinc.com/news/svante-to-deploy-first-of-a-kind-commercial-scale-carbon-capture-plant-at-delek-uss-texas-refinery-with-doe-support/?trk=feed_main-feed-card_feed-article-content | Y93: =IF(CCUS_Projects_Database!$R93<>"",HYPERLINK(CCUS_Projects_Database!$R93,"Link 1"),"") -> Link 1 | Z93: =IF(CCUS_Projects_Database!$S93<>"",HYPERLINK(CCUS_Projects_Database!$S93,"Link 2"),"") -> Link 2 | AA93: =IF(CCUS_Projects_Database!$T93<>"",HYPERLINK(CCUS_Projects_Database!$T93,"Link 3"),"") | AB93: =IF(CCUS_Projects_Database!$U93<>"",HYPERLINK(CCUS_Projects_Database!$U93,"Link 4"),"") | AC93: =IF(CCUS_Projects_Database!$V93<>"",HYPERLINK(CCUS_Projects_Database!$V93,"Link 5"),"") | AD93: =IF(CCUS_Projects_Database!$W93<>"",HYPERLINK(CCUS_Projects_Database!$W93,"Link 6"),"") | AE93: =IF(CCUS_Projects_Database!$X93<>"",HYPERLINK(CCUS_Projects_Database!$X93,"Link 7"),"")
A94: BIGST gas fiels Cluster Heads of Agreement | B94: 598 | C94: Malaysia | D94: Petronas, JX Nippon | E94: Full chain | F94: 2022 | J94: Planned | N94: Natural gas processing/LNG | O94: Dedicated storage | Q94: Other Asia Pacific | R94: https://www.petronas.com/media/media-releases/petronas-carigali-jx-nippon-enter-heads-agreement-bigst-cluster-offshore | Y94: =IF(CCUS_Projects_Database!$R94<>"",HYPERLINK(CCUS_Projects_Database!$R94,"Link 1"),"") -> Link 1 | Z94: =IF(CCUS_Projects_Database!$S94<>"",HYPERLINK(CCUS_Projects_Database!$S94,"Link 2"),"") | AA94: =IF(CCUS_Projects_Database!$T94<>"",HYPERLINK(CCUS_Projects_Database!$T94,"Link 3"),"") | AB94: =IF(CCUS_Projects_Database!$U94<>"",HYPERLINK(CCUS_Projects_Database!$U94,"Link 4"),"") | AC94: =IF(CCUS_Projects_Database!$V94<>"",HYPERLINK(CCUS_Projects_Database!$V94,"Link 5"),"") | AD94: =IF(CCUS_Projects_Database!$W94<>"",HYPERLINK(CCUS_Projects_Database!$W94,"Link 6"),"") | AE94: =IF(CCUS_Projects_Database!$X94<>"",HYPERLINK(CCUS_Projects_Database!$X94,"Link 7"),"")
A95: BIOFOS Carbon Capture Project | B95: 730 | C95: Denmark | D95: BIOFOS | E95: Capture | F95: 2021 | H95: 2030 | J95: Planned | N95: Power and heat | O95: Unknown/unspecified | Q95: Europe | Y95: =IF(CCUS_Projects_Database!$R95<>"",HYPERLINK(CCUS_Projects_Database!$R95,"Link 1"),"") | Z95: =IF(CCUS_Projects_Database!$S95<>"",HYPERLINK(CCUS_Projects_Database!$S95,"Link 2"),"") | AA95: =IF(CCUS_Projects_Database!$T95<>"",HYPERLINK(CCUS_Projects_Database!$T95,"Link 3"),"") | AB95: =IF(CCUS_Projects_Database!$U95<>"",HYPERLINK(CCUS_Projects_Database!$U95,"Link 4"),"") | AC95: =IF(CCUS_Projects_Database!$V95<>"",HYPERLINK(CCUS_Projects_Database!$V95,"Link 5"),"") | AD95: =IF(CCUS_Projects_Database!$W95<>"",HYPERLINK(CCUS_Projects_Database!$W95,"Link 6"),"") | AE95: =IF(CCUS_Projects_Database!$X95<>"",HYPERLINK(CCUS_Projects_Database!$X95,"Link 7"),"")
A96: BIR Waste-to-Energy Bergen | B96: 645 | C96: Norway | D96: BIR, Aker CC | E96: Capture | F96: 2021 | J96: Planned | L96: 0.1 | M96: 0.1 | N96: Power and heat | O96: Unknown/unspecified | Q96: Europe | R96: https://akercarboncapture.com/?cision_id=92D8BAC2851B0A03 | Y96: =IF(CCUS_Projects_Database!$R96<>"",HYPERLINK(CCUS_Projects_Database!$R96,"Link 1"),"") -> Link 1 | Z96: =IF(CCUS_Projects_Database!$S96<>"",HYPERLINK(CCUS_Projects_Database!$S96,"Link 2"),"") | AA96: =IF(CCUS_Projects_Database!$T96<>"",HYPERLINK(CCUS_Projects_Database!$T96,"Link 3"),"") | AB96: =IF(CCUS_Projects_Database!$U96<>"",HYPERLINK(CCUS_Projects_Database!$U96,"Link 4"),"") | AC96: =IF(CCUS_Projects_Database!$V96<>"",HYPERLINK(CCUS_Projects_Database!$V96,"Link 5"),"") | AD96: =IF(CCUS_Projects_Database!$W96<>"",HYPERLINK(CCUS_Projects_Database!$W96,"Link 6"),"") | AE96: =IF(CCUS_Projects_Database!$X96<>"",HYPERLINK(CCUS_Projects_Database!$X96,"Link 7"),"")
A97: Blue Bison ATR advanced CCUS system (WY) | B97: 697 | C97: United States | D97: Tallgrass MLP Operations, LLC (FEED) | E97: Capture | F97: 2021 | J97: Planned | L97: 1.66 | M97: 1.66 | N97: Hydrogen or ammonia | O97: Unknown/unspecified | Q97: North America | R97: https://www.netl.doe.gov/node/10875 | Y97: =IF(CCUS_Projects_Database!$R97<>"",HYPERLINK(CCUS_Projects_Database!$R97,"Link 1"),"") -> Link 1 | Z97: =IF(CCUS_Projects_Database!$S97<>"",HYPERLINK(CCUS_Projects_Database!$S97,"Link 2"),"") | AA97: =IF(CCUS_Projects_Database!$T97<>"",HYPERLINK(CCUS_Projects_Database!$T97,"Link 3"),"") | AB97: =IF(CCUS_Projects_Database!$U97<>"",HYPERLINK(CCUS_Projects_Database!$U97,"Link 4"),"") | AC97: =IF(CCUS_Projects_Database!$V97<>"",HYPERLINK(CCUS_Projects_Database!$V97,"Link 5"),"") | AD97: =IF(CCUS_Projects_Database!$W97<>"",HYPERLINK(CCUS_Projects_Database!$W97,"Link 6"),"") | AE97: =IF(CCUS_Projects_Database!$X97<>"",HYPERLINK(CCUS_Projects_Database!$X97,"Link 7"),"")
A98: BlueBonnet Sequestration Hub (Chambers, Liberty, and Jefferson County) (TX) | B98: 487 | C98: United States | D98: 1PointFive, Oxy low carbon ventures (Occidental) | E98: Storage | F98: 2022 | H98: 2026 | J98: Planned | L98: 8 | M98: 8 | N98: Storage | O98: Dedicated storage | P98: BlueBonnet sequestration hub | Q98: North America | R98: https://www.oxy.com/news/news-releases/oxy-low-carbon-ventures-and-natural-resource-partners-l.p.-enter-into-co2-sequestration-agreement/ | S98: https://www.1pointfive.com/1pointfive-announces-plan-to-develop-carbon-capture-and-sequestration-hub-in-southeast-texas | Y98: =IF(CCUS_Projects_Database!$R98<>"",HYPERLINK(CCUS_Projects_Database!$R98,"Link 1"),"") -> Link 1 | Z98: =IF(CCUS_Projects_Database!$S98<>"",HYPERLINK(CCUS_Projects_Database!$S98,"Link 2"),"") -> Link 2 | AA98: =IF(CCUS_Projects_Database!$T98<>"",HYPERLINK(CCUS_Projects_Database!$T98,"Link 3"),"") | AB98: =IF(CCUS_Projects_Database!$U98<>"",HYPERLINK(CCUS_Projects_Database!$U98,"Link 4"),"") | AC98: =IF(CCUS_Projects_Database!$V98<>"",HYPERLINK(CCUS_Projects_Database!$V98,"Link 5"),"") | AD98: =IF(CCUS_Projects_Database!$W98<>"",HYPERLINK(CCUS_Projects_Database!$W98,"Link 6"),"") | AE98: =IF(CCUS_Projects_Database!$X98<>"",HYPERLINK(CCUS_Projects_Database!$X98,"Link 7"),"")
A99: Bonanza BioEnergy CCUS (KS) | B99: 53 | C99: United States | D99: Conestoga Energy, Gary Climate Solutions Gary Climate Solutions | E99: Full chain | F99: 2010 | H99: 2012 | J99: Operational | L99: 0.13 | M99: 0.16 | N99: Biofuels | O99: EOR | Q99: North America | R99: https://www.geos.ed.ac.uk/sccs/project-info/2042 | S99: http://epubs.democratprinting.com/publication/?m=5729&i=39669&p=30&ver=html5 | T99: https://www.energy.gov/sites/prod/files/2017/12/f46/jordan_bioeconomy_2017.pdf | Y99: =IF(CCUS_Projects_Database!$R99<>"",HYPERLINK(CCUS_Projects_Database!$R99,"Link 1"),"") -> Link 1 | Z99: =IF(CCUS_Projects_Database!$S99<>"",HYPERLINK(CCUS_Projects_Database!$S99,"Link 2"),"") -> Link 2 | AA99: =IF(CCUS_Projects_Database!$T99<>"",HYPERLINK(CCUS_Projects_Database!$T99,"Link 3"),"") -> Link 3 | AB99: =IF(CCUS_Projects_Database!$U99<>"",HYPERLINK(CCUS_Projects_Database!$U99,"Link 4"),"") | AC99: =IF(CCUS_Projects_Database!$V99<>"",HYPERLINK(CCUS_Projects_Database!$V99,"Link 5"),"") | AD99: =IF(CCUS_Projects_Database!$W99<>"",HYPERLINK(CCUS_Projects_Database!$W99,"Link 6"),"") | AE99: =IF(CCUS_Projects_Database!$X99<>"",HYPERLINK(CCUS_Projects_Database!$X99,"Link 7"),"")
A100: Bonaparte CCS Assessment G7-AP | B100: 531 | C100: Australia | D100: Inpex (53%), TotalEnergies (26%), Woodside (21%, operator) | E100: Storage | F100: 2022 | H100: 2028 | J100: Planned | L100: 2 | M100: 2 | N100: Storage | O100: Dedicated storage | Q100: Australia and New Zealand | R100: https://totalenergies.com/media/news/press-releases/totalenergies-inpex-and-woodside-join-forces-develop-major-offshore-CO2-sequestration-project | S100: https://www.offshore-energy.biz/jogmec-to-support-inpexs-assessment-of-australian-ccs-potential/ | T100: https://public.neats.nopta.gov.au/ | U100: https://www.santos.com/news/santos-and-sk-es-to-collaborate-on-cross-border-carbon-capture-and-storage/ | Y100: =IF(CCUS_Projects_Database!$R100<>"",HYPERLINK(CCUS_Projects_Database!$R100,"Link 1"),"") -> Link 1 | Z100: =IF(CCUS_Projects_Database!$S100<>"",HYPERLINK(CCUS_Projects_Database!$S100,"Link 2"),"") -> Link 2 | AA100: =IF(CCUS_Projects_Database!$T100<>"",HYPERLINK(CCUS_Projects_Database!$T100,"Link 3"),"") -> Link 3 | AB100: =IF(CCUS_Projects_Database!$U100<>"",HYPERLINK(CCUS_Projects_Database!$U100,"Link 4"),"") -> Link 4 | AC100: =IF(CCUS_Projects_Database!$V100<>"",HYPERLINK(CCUS_Projects_Database!$V100,"Link 5"),"") | AD100: =IF(CCUS_Projects_Database!$W100<>"",HYPERLINK(CCUS_Projects_Database!$W100,"Link 6"),"") | AE100: =IF(CCUS_Projects_Database!$X100<>"",HYPERLINK(CCUS_Projects_Database!$X100,"Link 7"),"")
...
